pos_count.v
/*  UltiCores -- IP Cores for Mechatronic Control Systems
 *
 *  Copyright (C) 2019 UltiMachine <info@ultimachine.com>
 *
 *  Permission to use, copy, modify, and/or distribute this software for any
 *  purpose with or without fee is hereby granted, provided that the above
 *  copyright notice and this permission notice appear in all copies.
 *
 *  THE SOFTWARE IS PROVIDED "AS IS" AND THE AUTHOR DISCLAIMS ALL WARRANTIES
 *  WITH REGARD TO THIS SOFTWARE INCLUDING ALL IMPLIED WARRANTIES OF
 *  MERCHANTABILITY AND FITNESS. IN NO EVENT SHALL THE AUTHOR BE LIABLE FOR
 *  ANY SPECIAL, DIRECT, INDIRECT, OR CONSEQUENTIAL DAMAGES OR ANY DAMAGES
 *  WHATSOEVER RESULTING FROM LOSS OF USE, DATA OR PROFITS, WHETHER IN AN
 *  ACTION OF CONTRACT, NEGLIGENCE OR OTHER TORTIOUS ACTION, ARISING OUT OF
 *  OR IN CONNECTION WITH THE USE OR PERFORMANCE OF THIS SOFTWARE.
 */

/* quad_enc.v
 * Quadrature decoder inspired by https://www.fpga4fun.com/QuadratureDecoder.html
 * Converted to 32 bit. Added reset and fault logic. Changed some names to fit us.
 */

module pos_counter(
  input resetn,
  input clk,
  input step,
  input dir,
//  input step_on_edge, // If True, count on every step/dir change -Not implemented
  input step_active_high,  // If true, count when change to high
  input invert_dir, // Changes count up/down direction
  output reg [31:0] count
  );

//  wire faultn;

  reg [2:0] step_buf;  // Hold sample before compare for stability
  reg [1:0] dir_buf;

  wire step_edge = step_buf[1] ^ step_buf[2];  // Saw a signal level change if a changed
  wire active_edge = (step & step_active_high) | (step ~| step_active_high); // Is the edge we are triggering on the correct edge?
  wire stepped = step_edge & active_edge; // If the edge was the right polarity
  wire direction = dir_buf[1] ^ invert_dir;  //Direction determined by buffered input and config register

  always @(posedge clk) begin
    step_buf <= {step_buf[1:0], step};  //Shift new step in. Last 2 samples shift to bits 2 and 1 
    dir_buf <= {dir_buf[0], dir};  //Shift new dir in

    if (!resetn) begin
      count <= 0;  //reset count
    end
    else begin
      if (stepped) begin
        if (direction) 
          count <= count + 1;
        else 
          count <= count - 1;
      end
    end
  end
endmodule

pos_count_tb.v
/*  UltiCores -- IP Cores for Mechatronic Control Systems
 *
 *  Copyright (C) 2019 UltiMachine <info@ultimachine.com>
 *
 *  Permission to use, copy, modify, and/or distribute this software for any
 *  purpose with or without fee is hereby granted, provided that the above
 *  copyright notice and this permission notice appear in all copies.
 *
 *  THE SOFTWARE IS PROVIDED "AS IS" AND THE AUTHOR DISCLAIMS ALL WARRANTIES
 *  WITH REGARD TO THIS SOFTWARE INCLUDING ALL IMPLIED WARRANTIES OF
 *  MERCHANTABILITY AND FITNESS. IN NO EVENT SHALL THE AUTHOR BE LIABLE FOR
 *  ANY SPECIAL, DIRECT, INDIRECT, OR CONSEQUENTIAL DAMAGES OR ANY DAMAGES
 *  WHATSOEVER RESULTING FROM LOSS OF USE, DATA OR PROFITS, WHETHER IN AN
 *  ACTION OF CONTRACT, NEGLIGENCE OR OTHER TORTIOUS ACTION, ARISING OUT OF
 *  OR IN CONNECTION WITH THE USE OR PERFORMANCE OF THIS SOFTWARE.
 */

`include "pos_count.v"
`timescale 1ns/100ps

module testbench(
    input clk,
    output [31:0] count1,
    output [31:0] count2
  );
//  reg clk;
  wire resetn;
  reg step;
  reg dir;
  reg step_active_high;
  reg invert_dir;
//  reg [31:0] count;
  reg [7:0] resetn_counter = 0;

//  always #5 clk = (clk === 1'b0);

  assign resetn = &resetn_counter;

  always @(posedge clk) begin
    if (!resetn) resetn_counter <= resetn_counter +1;
  end

  pos_counter pos_counter1(.resetn(resetn), .clk(clk), .step(step), .dir(dir),
    .step_active_high(step_active_high), .invert_dir(invert_dir), .count(count1));
  pos_counter pos_counter2(.resetn(resetn), .clk(clk), .step(step), .dir(!dir),
    .step_active_high(step_active_high), .invert_dir(invert_dir), .count(count2));

  reg [20:0] cnt;
  initial begin
//    resetn = 0;
    step <= 0;
    dir <= 0;
    step_active_high <= 1;
    invert_dir <= 0;
    cnt <= 0;
  end

//  reg [3:0] enccntA = 0;
  reg [3:0] step_stim = 0;


  always @(posedge clk)
  begin
    if (!resetn) begin
      cnt <= 0;
      dir <= 0;
//      fault[7:2] <= 'b111111;
    end
    else begin
//    faultn <= &fault;
	    cnt <= cnt + 1;
            step_stim <= step_stim +1;
	    if (cnt <= 20'h40) begin
	      step <= step_stim[3];
	      dir <= 0;
	    end
	    else begin
	      step <= ~step_stim[3];
	      dir <= 1;
	    end
    end
  end

//  assign {LED0, LED1, LED2, LED3} = count1[3:0];
//  assign {LED4, LED5, LED6, LED7} = count1[7:4];


endmodule

pos_count.vcd
$scope module testbench $end
$var wire 1 n1 clk $end
$var wire 21 n2 cnt $end
$var wire 32 n3 count1 $end
$var wire 32 n4 count2 $end
$var wire 1 n5 dir $end
$var wire 1 n6 invert_dir $end
$var wire 1 n7 resetn $end
$var wire 8 n8 resetn_counter $end
$var wire 1 n9 step $end
$var wire 1 n10 step_active_high $end
$var wire 4 n11 step_stim $end
$scope module pos_counter2 $end
$var wire 1 n12 active_edge $end
$var wire 1 n13 clk $end
$var wire 32 n14 count $end
$var wire 1 n15 dir $end
$var wire 2 n16 dir_buf $end
$var wire 1 n17 direction $end
$var wire 1 n18 invert_dir $end
$var wire 1 n19 resetn $end
$var wire 1 n20 step $end
$var wire 1 n21 step_active_high $end
$var wire 3 n22 step_buf $end
$var wire 1 n23 step_edge $end
$var wire 1 n24 stepped $end
$upscope $end
$scope module pos_counter1 $end
$var wire 1 n25 active_edge $end
$var wire 1 n26 clk $end
$var wire 32 n27 count $end
$var wire 1 n28 dir $end
$var wire 2 n29 dir_buf $end
$var wire 1 n30 direction $end
$var wire 1 n31 invert_dir $end
$var wire 1 n32 resetn $end
$var wire 1 n33 step $end
$var wire 1 n34 step_active_high $end
$var wire 3 n35 step_buf $end
$var wire 1 n36 step_edge $end
$var wire 1 n37 stepped $end
$upscope $end
$upscope $end
$enddefinitions $end
#0
b0000 n11
b1 n10
b0 n9
b00000000 n8
b0 n7
b0 n6
b0 n5
bxxxxxxxxxxxxxxxxxxxxxxxxxxxxxxxx n4
bxxxxxxxxxxxxxxxxxxxxxxxxxxxxxxxx n3
b000000000000000000000 n2
bx n1
b0 n24
bx n23
bxxx n22
b1 n21
b0 n20
b0 n19
b0 n18
bx n17
bxx n16
b1 n15
bxxxxxxxxxxxxxxxxxxxxxxxxxxxxxxxx n14
bx n13
b0 n12
b0 n37
bx n36
bxxx n35
b1 n34
b0 n33
b0 n32
b0 n31
bx n30
bxx n29
b0 n28
bxxxxxxxxxxxxxxxxxxxxxxxxxxxxxxxx n27
bx n26
b0 n25
#5
b0 n1
b0 n13
b0 n26
#10
b00000001 n8
b00000000000000000000000000000000 n4
b00000000000000000000000000000000 n3
b1 n1
bxx0 n22
bx1 n16
b00000000000000000000000000000000 n14
b1 n13
bxx0 n35
bx0 n29
b00000000000000000000000000000000 n27
b1 n26
#15
b0 n1
b0 n13
b0 n26
#20
b00000010 n8
b1 n1
bx00 n22
b1 n17
b11 n16
b1 n13
bx00 n35
b0 n30
b00 n29
b1 n26
#25
b0 n1
b0 n13
b0 n26
#30
b00000011 n8
b1 n1
b0 n23
b000 n22
b1 n13
b0 n36
b000 n35
b1 n26
#35
b0 n1
b0 n13
b0 n26
#40
b00000100 n8
b1 n1
b1 n13
b1 n26
#45
b0 n1
b0 n13
b0 n26
#50
b00000101 n8
b1 n1
b1 n13
b1 n26
#55
b0 n1
b0 n13
b0 n26
#60
b00000110 n8
b1 n1
b1 n13
b1 n26
#65
b0 n1
b0 n13
b0 n26
#70
b00000111 n8
b1 n1
b1 n13
b1 n26
#75
b0 n1
b0 n13
b0 n26
#80
b00001000 n8
b1 n1
b1 n13
b1 n26
#85
b0 n1
b0 n13
b0 n26
#90
b00001001 n8
b1 n1
b1 n13
b1 n26
#95
b0 n1
b0 n13
b0 n26
#100
b00001010 n8
b1 n1
b1 n13
b1 n26
#105
b0 n1
b0 n13
b0 n26
#110
b00001011 n8
b1 n1
b1 n13
b1 n26
#115
b0 n1
b0 n13
b0 n26
#120
b00001100 n8
b1 n1
b1 n13
b1 n26
#125
b0 n1
b0 n13
b0 n26
#130
b00001101 n8
b1 n1
b1 n13
b1 n26
#135
b0 n1
b0 n13
b0 n26
#140
b00001110 n8
b1 n1
b1 n13
b1 n26
#145
b0 n1
b0 n13
b0 n26
#150
b00001111 n8
b1 n1
b1 n13
b1 n26
#155
b0 n1
b0 n13
b0 n26
#160
b00010000 n8
b1 n1
b1 n13
b1 n26
#165
b0 n1
b0 n13
b0 n26
#170
b00010001 n8
b1 n1
b1 n13
b1 n26
#175
b0 n1
b0 n13
b0 n26
#180
b00010010 n8
b1 n1
b1 n13
b1 n26
#185
b0 n1
b0 n13
b0 n26
#190
b00010011 n8
b1 n1
b1 n13
b1 n26
#195
b0 n1
b0 n13
b0 n26
#200
b00010100 n8
b1 n1
b1 n13
b1 n26
#205
b0 n1
b0 n13
b0 n26
#210
b00010101 n8
b1 n1
b1 n13
b1 n26
#215
b0 n1
b0 n13
b0 n26
#220
b00010110 n8
b1 n1
b1 n13
b1 n26
#225
b0 n1
b0 n13
b0 n26
#230
b00010111 n8
b1 n1
b1 n13
b1 n26
#235
b0 n1
b0 n13
b0 n26
#240
b00011000 n8
b1 n1
b1 n13
b1 n26
#245
b0 n1
b0 n13
b0 n26
#250
b00011001 n8
b1 n1
b1 n13
b1 n26
#255
b0 n1
b0 n13
b0 n26
#260
b00011010 n8
b1 n1
b1 n13
b1 n26
#265
b0 n1
b0 n13
b0 n26
#270
b00011011 n8
b1 n1
b1 n13
b1 n26
#275
b0 n1
b0 n13
b0 n26
#280
b00011100 n8
b1 n1
b1 n13
b1 n26
#285
b0 n1
b0 n13
b0 n26
#290
b00011101 n8
b1 n1
b1 n13
b1 n26
#295
b0 n1
b0 n13
b0 n26
#300
b00011110 n8
b1 n1
b1 n13
b1 n26
#305
b0 n1
b0 n13
b0 n26
#310
b00011111 n8
b1 n1
b1 n13
b1 n26
#315
b0 n1
b0 n13
b0 n26
#320
b00100000 n8
b1 n1
b1 n13
b1 n26
#325
b0 n1
b0 n13
b0 n26
#330
b00100001 n8
b1 n1
b1 n13
b1 n26
#335
b0 n1
b0 n13
b0 n26
#340
b00100010 n8
b1 n1
b1 n13
b1 n26
#345
b0 n1
b0 n13
b0 n26
#350
b00100011 n8
b1 n1
b1 n13
b1 n26
#355
b0 n1
b0 n13
b0 n26
#360
b00100100 n8
b1 n1
b1 n13
b1 n26
#365
b0 n1
b0 n13
b0 n26
#370
b00100101 n8
b1 n1
b1 n13
b1 n26
#375
b0 n1
b0 n13
b0 n26
#380
b00100110 n8
b1 n1
b1 n13
b1 n26
#385
b0 n1
b0 n13
b0 n26
#390
b00100111 n8
b1 n1
b1 n13
b1 n26
#395
b0 n1
b0 n13
b0 n26
#400
b00101000 n8
b1 n1
b1 n13
b1 n26
#405
b0 n1
b0 n13
b0 n26
#410
b00101001 n8
b1 n1
b1 n13
b1 n26
#415
b0 n1
b0 n13
b0 n26
#420
b00101010 n8
b1 n1
b1 n13
b1 n26
#425
b0 n1
b0 n13
b0 n26
#430
b00101011 n8
b1 n1
b1 n13
b1 n26
#435
b0 n1
b0 n13
b0 n26
#440
b00101100 n8
b1 n1
b1 n13
b1 n26
#445
b0 n1
b0 n13
b0 n26
#450
b00101101 n8
b1 n1
b1 n13
b1 n26
#455
b0 n1
b0 n13
b0 n26
#460
b00101110 n8
b1 n1
b1 n13
b1 n26
#465
b0 n1
b0 n13
b0 n26
#470
b00101111 n8
b1 n1
b1 n13
b1 n26
#475
b0 n1
b0 n13
b0 n26
#480
b00110000 n8
b1 n1
b1 n13
b1 n26
#485
b0 n1
b0 n13
b0 n26
#490
b00110001 n8
b1 n1
b1 n13
b1 n26
#495
b0 n1
b0 n13
b0 n26
#500
b00110010 n8
b1 n1
b1 n13
b1 n26
#505
b0 n1
b0 n13
b0 n26
#510
b00110011 n8
b1 n1
b1 n13
b1 n26
#515
b0 n1
b0 n13
b0 n26
#520
b00110100 n8
b1 n1
b1 n13
b1 n26
#525
b0 n1
b0 n13
b0 n26
#530
b00110101 n8
b1 n1
b1 n13
b1 n26
#535
b0 n1
b0 n13
b0 n26
#540
b00110110 n8
b1 n1
b1 n13
b1 n26
#545
b0 n1
b0 n13
b0 n26
#550
b00110111 n8
b1 n1
b1 n13
b1 n26
#555
b0 n1
b0 n13
b0 n26
#560
b00111000 n8
b1 n1
b1 n13
b1 n26
#565
b0 n1
b0 n13
b0 n26
#570
b00111001 n8
b1 n1
b1 n13
b1 n26
#575
b0 n1
b0 n13
b0 n26
#580
b00111010 n8
b1 n1
b1 n13
b1 n26
#585
b0 n1
b0 n13
b0 n26
#590
b00111011 n8
b1 n1
b1 n13
b1 n26
#595
b0 n1
b0 n13
b0 n26
#600
b00111100 n8
b1 n1
b1 n13
b1 n26
#605
b0 n1
b0 n13
b0 n26
#610
b00111101 n8
b1 n1
b1 n13
b1 n26
#615
b0 n1
b0 n13
b0 n26
#620
b00111110 n8
b1 n1
b1 n13
b1 n26
#625
b0 n1
b0 n13
b0 n26
#630
b00111111 n8
b1 n1
b1 n13
b1 n26
#635
b0 n1
b0 n13
b0 n26
#640
b01000000 n8
b1 n1
b1 n13
b1 n26
#645
b0 n1
b0 n13
b0 n26
#650
b01000001 n8
b1 n1
b1 n13
b1 n26
#655
b0 n1
b0 n13
b0 n26
#660
b01000010 n8
b1 n1
b1 n13
b1 n26
#665
b0 n1
b0 n13
b0 n26
#670
b01000011 n8
b1 n1
b1 n13
b1 n26
#675
b0 n1
b0 n13
b0 n26
#680
b01000100 n8
b1 n1
b1 n13
b1 n26
#685
b0 n1
b0 n13
b0 n26
#690
b01000101 n8
b1 n1
b1 n13
b1 n26
#695
b0 n1
b0 n13
b0 n26
#700
b01000110 n8
b1 n1
b1 n13
b1 n26
#705
b0 n1
b0 n13
b0 n26
#710
b01000111 n8
b1 n1
b1 n13
b1 n26
#715
b0 n1
b0 n13
b0 n26
#720
b01001000 n8
b1 n1
b1 n13
b1 n26
#725
b0 n1
b0 n13
b0 n26
#730
b01001001 n8
b1 n1
b1 n13
b1 n26
#735
b0 n1
b0 n13
b0 n26
#740
b01001010 n8
b1 n1
b1 n13
b1 n26
#745
b0 n1
b0 n13
b0 n26
#750
b01001011 n8
b1 n1
b1 n13
b1 n26
#755
b0 n1
b0 n13
b0 n26
#760
b01001100 n8
b1 n1
b1 n13
b1 n26
#765
b0 n1
b0 n13
b0 n26
#770
b01001101 n8
b1 n1
b1 n13
b1 n26
#775
b0 n1
b0 n13
b0 n26
#780
b01001110 n8
b1 n1
b1 n13
b1 n26
#785
b0 n1
b0 n13
b0 n26
#790
b01001111 n8
b1 n1
b1 n13
b1 n26
#795
b0 n1
b0 n13
b0 n26
#800
b01010000 n8
b1 n1
b1 n13
b1 n26
#805
b0 n1
b0 n13
b0 n26
#810
b01010001 n8
b1 n1
b1 n13
b1 n26
#815
b0 n1
b0 n13
b0 n26
#820
b01010010 n8
b1 n1
b1 n13
b1 n26
#825
b0 n1
b0 n13
b0 n26
#830
b01010011 n8
b1 n1
b1 n13
b1 n26
#835
b0 n1
b0 n13
b0 n26
#840
b01010100 n8
b1 n1
b1 n13
b1 n26
#845
b0 n1
b0 n13
b0 n26
#850
b01010101 n8
b1 n1
b1 n13
b1 n26
#855
b0 n1
b0 n13
b0 n26
#860
b01010110 n8
b1 n1
b1 n13
b1 n26
#865
b0 n1
b0 n13
b0 n26
#870
b01010111 n8
b1 n1
b1 n13
b1 n26
#875
b0 n1
b0 n13
b0 n26
#880
b01011000 n8
b1 n1
b1 n13
b1 n26
#885
b0 n1
b0 n13
b0 n26
#890
b01011001 n8
b1 n1
b1 n13
b1 n26
#895
b0 n1
b0 n13
b0 n26
#900
b01011010 n8
b1 n1
b1 n13
b1 n26
#905
b0 n1
b0 n13
b0 n26
#910
b01011011 n8
b1 n1
b1 n13
b1 n26
#915
b0 n1
b0 n13
b0 n26
#920
b01011100 n8
b1 n1
b1 n13
b1 n26
#925
b0 n1
b0 n13
b0 n26
#930
b01011101 n8
b1 n1
b1 n13
b1 n26
#935
b0 n1
b0 n13
b0 n26
#940
b01011110 n8
b1 n1
b1 n13
b1 n26
#945
b0 n1
b0 n13
b0 n26
#950
b01011111 n8
b1 n1
b1 n13
b1 n26
#955
b0 n1
b0 n13
b0 n26
#960
b01100000 n8
b1 n1
b1 n13
b1 n26
#965
b0 n1
b0 n13
b0 n26
#970
b01100001 n8
b1 n1
b1 n13
b1 n26
#975
b0 n1
b0 n13
b0 n26
#980
b01100010 n8
b1 n1
b1 n13
b1 n26
#985
b0 n1
b0 n13
b0 n26
#990
b01100011 n8
b1 n1
b1 n13
b1 n26
#995
b0 n1
b0 n13
b0 n26
#1000
b01100100 n8
b1 n1
b1 n13
b1 n26
#1005
b0 n1
b0 n13
b0 n26
#1010
b01100101 n8
b1 n1
b1 n13
b1 n26
#1015
b0 n1
b0 n13
b0 n26
#1020
b01100110 n8
b1 n1
b1 n13
b1 n26
#1025
b0 n1
b0 n13
b0 n26
#1030
b01100111 n8
b1 n1
b1 n13
b1 n26
#1035
b0 n1
b0 n13
b0 n26
#1040
b01101000 n8
b1 n1
b1 n13
b1 n26
#1045
b0 n1
b0 n13
b0 n26
#1050
b01101001 n8
b1 n1
b1 n13
b1 n26
#1055
b0 n1
b0 n13
b0 n26
#1060
b01101010 n8
b1 n1
b1 n13
b1 n26
#1065
b0 n1
b0 n13
b0 n26
#1070
b01101011 n8
b1 n1
b1 n13
b1 n26
#1075
b0 n1
b0 n13
b0 n26
#1080
b01101100 n8
b1 n1
b1 n13
b1 n26
#1085
b0 n1
b0 n13
b0 n26
#1090
b01101101 n8
b1 n1
b1 n13
b1 n26
#1095
b0 n1
b0 n13
b0 n26
#1100
b01101110 n8
b1 n1
b1 n13
b1 n26
#1105
b0 n1
b0 n13
b0 n26
#1110
b01101111 n8
b1 n1
b1 n13
b1 n26
#1115
b0 n1
b0 n13
b0 n26
#1120
b01110000 n8
b1 n1
b1 n13
b1 n26
#1125
b0 n1
b0 n13
b0 n26
#1130
b01110001 n8
b1 n1
b1 n13
b1 n26
#1135
b0 n1
b0 n13
b0 n26
#1140
b01110010 n8
b1 n1
b1 n13
b1 n26
#1145
b0 n1
b0 n13
b0 n26
#1150
b01110011 n8
b1 n1
b1 n13
b1 n26
#1155
b0 n1
b0 n13
b0 n26
#1160
b01110100 n8
b1 n1
b1 n13
b1 n26
#1165
b0 n1
b0 n13
b0 n26
#1170
b01110101 n8
b1 n1
b1 n13
b1 n26
#1175
b0 n1
b0 n13
b0 n26
#1180
b01110110 n8
b1 n1
b1 n13
b1 n26
#1185
b0 n1
b0 n13
b0 n26
#1190
b01110111 n8
b1 n1
b1 n13
b1 n26
#1195
b0 n1
b0 n13
b0 n26
#1200
b01111000 n8
b1 n1
b1 n13
b1 n26
#1205
b0 n1
b0 n13
b0 n26
#1210
b01111001 n8
b1 n1
b1 n13
b1 n26
#1215
b0 n1
b0 n13
b0 n26
#1220
b01111010 n8
b1 n1
b1 n13
b1 n26
#1225
b0 n1
b0 n13
b0 n26
#1230
b01111011 n8
b1 n1
b1 n13
b1 n26
#1235
b0 n1
b0 n13
b0 n26
#1240
b01111100 n8
b1 n1
b1 n13
b1 n26
#1245
b0 n1
b0 n13
b0 n26
#1250
b01111101 n8
b1 n1
b1 n13
b1 n26
#1255
b0 n1
b0 n13
b0 n26
#1260
b01111110 n8
b1 n1
b1 n13
b1 n26
#1265
b0 n1
b0 n13
b0 n26
#1270
b01111111 n8
b1 n1
b1 n13
b1 n26
#1275
b0 n1
b0 n13
b0 n26
#1280
b10000000 n8
b1 n1
b1 n13
b1 n26
#1285
b0 n1
b0 n13
b0 n26
#1290
b10000001 n8
b1 n1
b1 n13
b1 n26
#1295
b0 n1
b0 n13
b0 n26
#1300
b10000010 n8
b1 n1
b1 n13
b1 n26
#1305
b0 n1
b0 n13
b0 n26
#1310
b10000011 n8
b1 n1
b1 n13
b1 n26
#1315
b0 n1
b0 n13
b0 n26
#1320
b10000100 n8
b1 n1
b1 n13
b1 n26
#1325
b0 n1
b0 n13
b0 n26
#1330
b10000101 n8
b1 n1
b1 n13
b1 n26
#1335
b0 n1
b0 n13
b0 n26
#1340
b10000110 n8
b1 n1
b1 n13
b1 n26
#1345
b0 n1
b0 n13
b0 n26
#1350
b10000111 n8
b1 n1
b1 n13
b1 n26
#1355
b0 n1
b0 n13
b0 n26
#1360
b10001000 n8
b1 n1
b1 n13
b1 n26
#1365
b0 n1
b0 n13
b0 n26
#1370
b10001001 n8
b1 n1
b1 n13
b1 n26
#1375
b0 n1
b0 n13
b0 n26
#1380
b10001010 n8
b1 n1
b1 n13
b1 n26
#1385
b0 n1
b0 n13
b0 n26
#1390
b10001011 n8
b1 n1
b1 n13
b1 n26
#1395
b0 n1
b0 n13
b0 n26
#1400
b10001100 n8
b1 n1
b1 n13
b1 n26
#1405
b0 n1
b0 n13
b0 n26
#1410
b10001101 n8
b1 n1
b1 n13
b1 n26
#1415
b0 n1
b0 n13
b0 n26
#1420
b10001110 n8
b1 n1
b1 n13
b1 n26
#1425
b0 n1
b0 n13
b0 n26
#1430
b10001111 n8
b1 n1
b1 n13
b1 n26
#1435
b0 n1
b0 n13
b0 n26
#1440
b10010000 n8
b1 n1
b1 n13
b1 n26
#1445
b0 n1
b0 n13
b0 n26
#1450
b10010001 n8
b1 n1
b1 n13
b1 n26
#1455
b0 n1
b0 n13
b0 n26
#1460
b10010010 n8
b1 n1
b1 n13
b1 n26
#1465
b0 n1
b0 n13
b0 n26
#1470
b10010011 n8
b1 n1
b1 n13
b1 n26
#1475
b0 n1
b0 n13
b0 n26
#1480
b10010100 n8
b1 n1
b1 n13
b1 n26
#1485
b0 n1
b0 n13
b0 n26
#1490
b10010101 n8
b1 n1
b1 n13
b1 n26
#1495
b0 n1
b0 n13
b0 n26
#1500
b10010110 n8
b1 n1
b1 n13
b1 n26
#1505
b0 n1
b0 n13
b0 n26
#1510
b10010111 n8
b1 n1
b1 n13
b1 n26
#1515
b0 n1
b0 n13
b0 n26
#1520
b10011000 n8
b1 n1
b1 n13
b1 n26
#1525
b0 n1
b0 n13
b0 n26
#1530
b10011001 n8
b1 n1
b1 n13
b1 n26
#1535
b0 n1
b0 n13
b0 n26
#1540
b10011010 n8
b1 n1
b1 n13
b1 n26
#1545
b0 n1
b0 n13
b0 n26
#1550
b10011011 n8
b1 n1
b1 n13
b1 n26
#1555
b0 n1
b0 n13
b0 n26
#1560
b10011100 n8
b1 n1
b1 n13
b1 n26
#1565
b0 n1
b0 n13
b0 n26
#1570
b10011101 n8
b1 n1
b1 n13
b1 n26
#1575
b0 n1
b0 n13
b0 n26
#1580
b10011110 n8
b1 n1
b1 n13
b1 n26
#1585
b0 n1
b0 n13
b0 n26
#1590
b10011111 n8
b1 n1
b1 n13
b1 n26
#1595
b0 n1
b0 n13
b0 n26
#1600
b10100000 n8
b1 n1
b1 n13
b1 n26
#1605
b0 n1
b0 n13
b0 n26
#1610
b10100001 n8
b1 n1
b1 n13
b1 n26
#1615
b0 n1
b0 n13
b0 n26
#1620
b10100010 n8
b1 n1
b1 n13
b1 n26
#1625
b0 n1
b0 n13
b0 n26
#1630
b10100011 n8
b1 n1
b1 n13
b1 n26
#1635
b0 n1
b0 n13
b0 n26
#1640
b10100100 n8
b1 n1
b1 n13
b1 n26
#1645
b0 n1
b0 n13
b0 n26
#1650
b10100101 n8
b1 n1
b1 n13
b1 n26
#1655
b0 n1
b0 n13
b0 n26
#1660
b10100110 n8
b1 n1
b1 n13
b1 n26
#1665
b0 n1
b0 n13
b0 n26
#1670
b10100111 n8
b1 n1
b1 n13
b1 n26
#1675
b0 n1
b0 n13
b0 n26
#1680
b10101000 n8
b1 n1
b1 n13
b1 n26
#1685
b0 n1
b0 n13
b0 n26
#1690
b10101001 n8
b1 n1
b1 n13
b1 n26
#1695
b0 n1
b0 n13
b0 n26
#1700
b10101010 n8
b1 n1
b1 n13
b1 n26
#1705
b0 n1
b0 n13
b0 n26
#1710
b10101011 n8
b1 n1
b1 n13
b1 n26
#1715
b0 n1
b0 n13
b0 n26
#1720
b10101100 n8
b1 n1
b1 n13
b1 n26
#1725
b0 n1
b0 n13
b0 n26
#1730
b10101101 n8
b1 n1
b1 n13
b1 n26
#1735
b0 n1
b0 n13
b0 n26
#1740
b10101110 n8
b1 n1
b1 n13
b1 n26
#1745
b0 n1
b0 n13
b0 n26
#1750
b10101111 n8
b1 n1
b1 n13
b1 n26
#1755
b0 n1
b0 n13
b0 n26
#1760
b10110000 n8
b1 n1
b1 n13
b1 n26
#1765
b0 n1
b0 n13
b0 n26
#1770
b10110001 n8
b1 n1
b1 n13
b1 n26
#1775
b0 n1
b0 n13
b0 n26
#1780
b10110010 n8
b1 n1
b1 n13
b1 n26
#1785
b0 n1
b0 n13
b0 n26
#1790
b10110011 n8
b1 n1
b1 n13
b1 n26
#1795
b0 n1
b0 n13
b0 n26
#1800
b10110100 n8
b1 n1
b1 n13
b1 n26
#1805
b0 n1
b0 n13
b0 n26
#1810
b10110101 n8
b1 n1
b1 n13
b1 n26
#1815
b0 n1
b0 n13
b0 n26
#1820
b10110110 n8
b1 n1
b1 n13
b1 n26
#1825
b0 n1
b0 n13
b0 n26
#1830
b10110111 n8
b1 n1
b1 n13
b1 n26
#1835
b0 n1
b0 n13
b0 n26
#1840
b10111000 n8
b1 n1
b1 n13
b1 n26
#1845
b0 n1
b0 n13
b0 n26
#1850
b10111001 n8
b1 n1
b1 n13
b1 n26
#1855
b0 n1
b0 n13
b0 n26
#1860
b10111010 n8
b1 n1
b1 n13
b1 n26
#1865
b0 n1
b0 n13
b0 n26
#1870
b10111011 n8
b1 n1
b1 n13
b1 n26
#1875
b0 n1
b0 n13
b0 n26
#1880
b10111100 n8
b1 n1
b1 n13
b1 n26
#1885
b0 n1
b0 n13
b0 n26
#1890
b10111101 n8
b1 n1
b1 n13
b1 n26
#1895
b0 n1
b0 n13
b0 n26
#1900
b10111110 n8
b1 n1
b1 n13
b1 n26
#1905
b0 n1
b0 n13
b0 n26
#1910
b10111111 n8
b1 n1
b1 n13
b1 n26
#1915
b0 n1
b0 n13
b0 n26
#1920
b11000000 n8
b1 n1
b1 n13
b1 n26
#1925
b0 n1
b0 n13
b0 n26
#1930
b11000001 n8
b1 n1
b1 n13
b1 n26
#1935
b0 n1
b0 n13
b0 n26
#1940
b11000010 n8
b1 n1
b1 n13
b1 n26
#1945
b0 n1
b0 n13
b0 n26
#1950
b11000011 n8
b1 n1
b1 n13
b1 n26
#1955
b0 n1
b0 n13
b0 n26
#1960
b11000100 n8
b1 n1
b1 n13
b1 n26
#1965
b0 n1
b0 n13
b0 n26
#1970
b11000101 n8
b1 n1
b1 n13
b1 n26
#1975
b0 n1
b0 n13
b0 n26
#1980
b11000110 n8
b1 n1
b1 n13
b1 n26
#1985
b0 n1
b0 n13
b0 n26
#1990
b11000111 n8
b1 n1
b1 n13
b1 n26
#1995
b0 n1
b0 n13
b0 n26
#2000
b11001000 n8
b1 n1
b1 n13
b1 n26
#2005
b0 n1
b0 n13
b0 n26
#2010
b11001001 n8
b1 n1
b1 n13
b1 n26
#2015
b0 n1
b0 n13
b0 n26
#2020
b11001010 n8
b1 n1
b1 n13
b1 n26
#2025
b0 n1
b0 n13
b0 n26
#2030
b11001011 n8
b1 n1
b1 n13
b1 n26
#2035
b0 n1
b0 n13
b0 n26
#2040
b11001100 n8
b1 n1
b1 n13
b1 n26
#2045
b0 n1
b0 n13
b0 n26
#2050
b11001101 n8
b1 n1
b1 n13
b1 n26
#2055
b0 n1
b0 n13
b0 n26
#2060
b11001110 n8
b1 n1
b1 n13
b1 n26
#2065
b0 n1
b0 n13
b0 n26
#2070
b11001111 n8
b1 n1
b1 n13
b1 n26
#2075
b0 n1
b0 n13
b0 n26
#2080
b11010000 n8
b1 n1
b1 n13
b1 n26
#2085
b0 n1
b0 n13
b0 n26
#2090
b11010001 n8
b1 n1
b1 n13
b1 n26
#2095
b0 n1
b0 n13
b0 n26
#2100
b11010010 n8
b1 n1
b1 n13
b1 n26
#2105
b0 n1
b0 n13
b0 n26
#2110
b11010011 n8
b1 n1
b1 n13
b1 n26
#2115
b0 n1
b0 n13
b0 n26
#2120
b11010100 n8
b1 n1
b1 n13
b1 n26
#2125
b0 n1
b0 n13
b0 n26
#2130
b11010101 n8
b1 n1
b1 n13
b1 n26
#2135
b0 n1
b0 n13
b0 n26
#2140
b11010110 n8
b1 n1
b1 n13
b1 n26
#2145
b0 n1
b0 n13
b0 n26
#2150
b11010111 n8
b1 n1
b1 n13
b1 n26
#2155
b0 n1
b0 n13
b0 n26
#2160
b11011000 n8
b1 n1
b1 n13
b1 n26
#2165
b0 n1
b0 n13
b0 n26
#2170
b11011001 n8
b1 n1
b1 n13
b1 n26
#2175
b0 n1
b0 n13
b0 n26
#2180
b11011010 n8
b1 n1
b1 n13
b1 n26
#2185
b0 n1
b0 n13
b0 n26
#2190
b11011011 n8
b1 n1
b1 n13
b1 n26
#2195
b0 n1
b0 n13
b0 n26
#2200
b11011100 n8
b1 n1
b1 n13
b1 n26
#2205
b0 n1
b0 n13
b0 n26
#2210
b11011101 n8
b1 n1
b1 n13
b1 n26
#2215
b0 n1
b0 n13
b0 n26
#2220
b11011110 n8
b1 n1
b1 n13
b1 n26
#2225
b0 n1
b0 n13
b0 n26
#2230
b11011111 n8
b1 n1
b1 n13
b1 n26
#2235
b0 n1
b0 n13
b0 n26
#2240
b11100000 n8
b1 n1
b1 n13
b1 n26
