quad_enc.v
/*
 *
 *  UltiCores -- IP Cores for Mechatronic Control Systems
 *
 *  Copyright (C) 2019 UltiMachine <info@ultimachine.com>
 *
 *  Permission to use, copy, modify, and/or distribute this software for any
 *  purpose with or without fee is hereby granted, provided that the above
 *  copyright notice and this permission notice appear in all copies.
 *
 *  THE SOFTWARE IS PROVIDED "AS IS" AND THE AUTHOR DISCLAIMS ALL WARRANTIES
 *  WITH REGARD TO THIS SOFTWARE INCLUDING ALL IMPLIED WARRANTIES OF
 *  MERCHANTABILITY AND FITNESS. IN NO EVENT SHALL THE AUTHOR BE LIABLE FOR
 *  ANY SPECIAL, DIRECT, INDIRECT, OR CONSEQUENTIAL DAMAGES OR ANY DAMAGES
 *  WHATSOEVER RESULTING FROM LOSS OF USE, DATA OR PROFITS, WHETHER IN AN
 *  ACTION OF CONTRACT, NEGLIGENCE OR OTHER TORTIOUS ACTION, ARISING OUT OF
 *  OR IN CONNECTION WITH THE USE OR PERFORMANCE OF THIS SOFTWARE.
 *
 */

module quad_enc(
  input resetn,
  input clk,
  input a,
  input b,
  output reg faultn,
  output reg [15:0] count
  );

//  wire faultn;

  reg [2:0] a_stable, b_stable;  //Hold sample before compare for stability

  wire step_a = a_stable[1] ^ a_stable[2];  //Step if a changed
  wire step_b = b_stable[1] ^ b_stable[2];  //Step if b changed
  wire step = step_a ^ step_b;  //Step if a xor b stepped
  wire direction = a_stable[1] ^ b_stable[2];  //Direction determined by comparing current sample to last

  always @(posedge clk) begin
    a_stable <= {a_stable[1:0], a};  //Shift new a in. Last 2 samples shift to bits 2 and 1 
    b_stable <= {b_stable[1:0], b};  //Shift new b in

    if (!resetn) begin
      count <= 0;  //reset count
      faultn <= 1; //reset faultn
    end
    else begin
      if (step_a && step_b)  //We do not know direction if both inputs triggered on single clock
        faultn <= 0;
      if (step) begin
        if (direction) 
          count <= count + 1;
        else 
          count <= count - 1;
          faultn <= faultn;
      end
    end
  end
endmodule

quad_testbench.v
/*
 *
 *  UltiCores -- IP Cores for Mechatronic Control Systems
 *
 *  Copyright (C) 2019 UltiMachine <info@ultimachine.com>
 *
 *  Permission to use, copy, modify, and/or distribute this software for any
 *  purpose with or without fee is hereby granted, provided that the above
 *  copyright notice and this permission notice appear in all copies.
 *
 *  THE SOFTWARE IS PROVIDED "AS IS" AND THE AUTHOR DISCLAIMS ALL WARRANTIES
 *  WITH REGARD TO THIS SOFTWARE INCLUDING ALL IMPLIED WARRANTIES OF
 *  MERCHANTABILITY AND FITNESS. IN NO EVENT SHALL THE AUTHOR BE LIABLE FOR
 *  ANY SPECIAL, DIRECT, INDIRECT, OR CONSEQUENTIAL DAMAGES OR ANY DAMAGES
 *  WHATSOEVER RESULTING FROM LOSS OF USE, DATA OR PROFITS, WHETHER IN AN
 *  ACTION OF CONTRACT, NEGLIGENCE OR OTHER TORTIOUS ACTION, ARISING OUT OF
 *  OR IN CONNECTION WITH THE USE OR PERFORMANCE OF THIS SOFTWARE.
 *
 */

`include "quad_enc.v"
`timescale 1ns/100ps

module top(
  input clk, 
  output enc1a, //Changed for sim
  output enc1b, //Changed for sim
  output enc2a, //Changed for sim
  output enc2b, //Changed for sim
  output LED0,
  output LED1,
  output LED2,
  output LED3,
  output LED4,
  output LED5,
  output LED6,
  output LED7,
  output faultn
  );

  reg enc1a, enc1b, enc2a, enc2b;
  wire [15:0] count1, count2;
//  reg resetn;
  wire resetn;
  reg [7:0] resetn_counter = 0;
  wire faultn;
  reg [7:0] fault;

  assign resetn = &resetn_counter;

  always @(posedge clk) begin
    if (!resetn) resetn_counter <= resetn_counter +1;
  end

  quad_enc quad1(.resetn(resetn), .clk(clk), .a(enc1a), .b(enc1b), .count(count1), .faultn(fault[0]));
  quad_enc quad2(.resetn(resetn), .clk(clk), .a(enc2a), .b(enc2b), .count(count2), .faultn(fault[1]));


  reg [20:0] cnt;
  initial begin
    enc1a <= 0;
    enc1b <= 0;
    enc2a <= 0;
    enc2b <= 0;
    cnt <= 0;
  end

  reg [3:0] enccntA = 0;
  reg [3:0] enccntB = 4;


  always @(posedge clk)
  begin
    if (!resetn) begin
      cnt <= 0;
      fault[7:2] <= 'b111111;
    end
    faultn <= &fault;
    cnt <= cnt + 1;
    if (cnt <= 20'h90) begin
      enccntA <= enccntA + 1;
      enc1a <= enccntA[3];
      enccntB <= enccntB - 1;
      enc1b <= enccntB[3];
      enc2a <= enc1b;
      enc2b <= enc1a;
    end
    else begin
      cnt <=0;
      enc2a <= ~enc2a;  //Inject fault in encoder 2
      enc2b <= ~enc2b;
    end
  end

  assign {LED0, LED1, LED2, LED3} = count1[3:0];
  assign {LED4, LED5, LED6, LED7} = count2[3:0];


endmodule

quad_enc.vcd
$scope module top $end
$var wire 1 n1 LED0 $end
$var wire 1 n2 LED1 $end
$var wire 1 n3 LED2 $end
$var wire 1 n4 LED3 $end
$var wire 1 n5 LED4 $end
$var wire 1 n6 LED5 $end
$var wire 1 n7 LED6 $end
$var wire 1 n8 LED7 $end
$var wire 1 n9 clk $end
$var wire 21 n10 cnt $end
$var wire 16 n11 count1 $end
$var wire 16 n12 count2 $end
$var wire 1 n13 enc1a $end
$var wire 1 n14 enc1b $end
$var wire 1 n15 enc2a $end
$var wire 1 n16 enc2b $end
$var wire 4 n17 enccntA $end
$var wire 4 n18 enccntB $end
$var wire 8 n19 fault $end
$var wire 1 n20 faultn $end
$var wire 1 n21 resetn $end
$var wire 8 n22 resetn_counter $end
$scope module quad2 $end
$var wire 1 n23 a $end
$var wire 3 n24 a_stable $end
$var wire 1 n25 b $end
$var wire 3 n26 b_stable $end
$var wire 1 n27 clk $end
$var wire 16 n28 count $end
$var wire 1 n29 direction $end
$var wire 1 n30 faultn $end
$var wire 1 n31 resetn $end
$var wire 1 n32 step $end
$var wire 1 n33 step_a $end
$var wire 1 n34 step_b $end
$upscope $end
$scope module quad1 $end
$var wire 1 n35 a $end
$var wire 3 n36 a_stable $end
$var wire 1 n37 b $end
$var wire 3 n38 b_stable $end
$var wire 1 n39 clk $end
$var wire 16 n40 count $end
$var wire 1 n41 direction $end
$var wire 1 n42 faultn $end
$var wire 1 n43 resetn $end
$var wire 1 n44 step $end
$var wire 1 n45 step_a $end
$var wire 1 n46 step_b $end
$upscope $end
$upscope $end
$enddefinitions $end
#0
b00000000 n22
b0 n21
bx n20
bxxxxxxxx n19
b0100 n18
b0000 n17
b0 n16
b0 n15
b0 n14
b0 n13
bxxxxxxxxxxxxxxxx n12
bxxxxxxxxxxxxxxxx n11
b000000000000000000000 n10
bx n9
bx n8
bx n7
bx n6
bx n5
bx n4
bx n3
bx n2
bx n1
bx n34
bx n33
bx n32
b0 n31
bx n30
bx n29
bxxxxxxxxxxxxxxxx n28
bx n27
bxxx n26
b0 n25
bxxx n24
b0 n23
bx n46
bx n45
bx n44
b0 n43
bx n42
bx n41
bxxxxxxxxxxxxxxxx n40
bx n39
bxxx n38
b0 n37
bxxx n36
b0 n35
#5
b0 n9
b0 n27
b0 n39
#10
b00000001 n22
b11111111 n19
b0011 n18
b0001 n17
b0000000000000000 n12
b0000000000000000 n11
b000000000000000000001 n10
b1 n9
b0 n8
b0 n7
b0 n6
b0 n5
b0 n4
b0 n3
b0 n2
b0 n1
b1 n30
b0000000000000000 n28
b1 n27
bxx0 n26
bxx0 n24
b1 n42
b0000000000000000 n40
b1 n39
bxx0 n38
bxx0 n36
#15
b0 n9
b0 n27
b0 n39
#20
b00000010 n22
b1 n20
b0010 n18
b0010 n17
b000000000000000000010 n10
b1 n9
b1 n27
bx00 n26
bx00 n24
b1 n39
bx00 n38
bx00 n36
#25
b0 n9
b0 n27
b0 n39
#30
b00000011 n22
b0001 n18
b0011 n17
b000000000000000000011 n10
b1 n9
b0 n34
b0 n33
b0 n32
b0 n29
b1 n27
b000 n26
b000 n24
b0 n46
b0 n45
b0 n44
b0 n41
b1 n39
b000 n38
b000 n36
#35
b0 n9
b0 n27
b0 n39
#40
b00000100 n22
b0000 n18
b0100 n17
b000000000000000000100 n10
b1 n9
b1 n27
b1 n39
#45
b0 n9
b0 n27
b0 n39
#50
b00000101 n22
b1111 n18
b0101 n17
b000000000000000000101 n10
b1 n9
b1 n27
b1 n39
#55
b0 n9
b0 n27
b0 n39
#60
b00000110 n22
b1110 n18
b0110 n17
b1 n14
b000000000000000000110 n10
b1 n9
b1 n27
b1 n39
b1 n37
#65
b0 n9
b0 n27
b0 n39
#70
b00000111 n22
b1101 n18
b0111 n17
b1 n15
b000000000000000000111 n10
b1 n9
b1 n27
b1 n23
b1 n39
b001 n38
#75
b0 n9
b0 n27
b0 n39
#80
b00001000 n22
b1100 n18
b1000 n17
b000000000000000001000 n10
b1 n9
b1 n27
b001 n24
b1 n46
b1 n44
b1 n39
b011 n38
#85
b0 n9
b0 n27
b0 n39
#90
b00001001 n22
b1011 n18
b1001 n17
b1 n13
b000000000000000001001 n10
b1 n9
b1 n33
b1 n32
b1 n29
b1 n27
b011 n24
b0 n46
b0 n44
b1 n41
b1 n39
b111 n38
b1 n35
#95
b0 n9
b0 n27
b0 n39
#100
b00001010 n22
b1010 n18
b1010 n17
b1 n16
b000000000000000001010 n10
b1 n9
b0 n33
b0 n32
b1 n27
b1 n25
b111 n24
b1 n39
b001 n36
#105
b0 n9
b0 n27
b0 n39
#110
b00001011 n22
b1001 n18
b1011 n17
b000000000000000001011 n10
b1 n9
b1 n27
b001 n26
b1 n45
b1 n44
b0 n41
b1 n39
b011 n36
#115
b0 n9
b0 n27
b0 n39
#120
b00001100 n22
b1000 n18
b1100 n17
b000000000000000001100 n10
b1 n9
b1 n34
b1 n32
b1 n27
b011 n26
b0 n45
b0 n44
b1 n39
b111 n36
#125
b0 n9
b0 n27
b0 n39
#130
b00001101 n22
b0111 n18
b1101 n17
b000000000000000001101 n10
b1 n9
b0 n34
b0 n32
b0 n29
b1 n27
b111 n26
b1 n39
#135
b0 n9
b0 n27
b0 n39
#140
b00001110 n22
b0110 n18
b1110 n17
b0 n14
b000000000000000001110 n10
b1 n9
b1 n27
b1 n39
b0 n37
#145
b0 n9
b0 n27
b0 n39
#150
b00001111 n22
b0101 n18
b1111 n17
b0 n15
b000000000000000001111 n10
b1 n9
b1 n27
b0 n23
b1 n39
b110 n38
#155
b0 n9
b0 n27
b0 n39
#160
b00010000 n22
b0100 n18
b0000 n17
b000000000000000010000 n10
b1 n9
b1 n27
b110 n24
b1 n46
b1 n44
b1 n39
b100 n38
#165
b0 n9
b0 n27
b0 n39
#170
b00010001 n22
b0011 n18
b0001 n17
b0 n13
b000000000000000010001 n10
b1 n9
b1 n33
b1 n32
b1 n29
b1 n27
b100 n24
b0 n46
b0 n44
b1 n41
b1 n39
b000 n38
b0 n35
#175
b0 n9
b0 n27
b0 n39
#180
b00010010 n22
b0010 n18
b0010 n17
b0 n16
b000000000000000010010 n10
b1 n9
b0 n33
b0 n32
b1 n27
b0 n25
b000 n24
b1 n39
b110 n36
#185
b0 n9
b0 n27
b0 n39
#190
b00010011 n22
b0001 n18
b0011 n17
b000000000000000010011 n10
b1 n9
b1 n27
b110 n26
b1 n45
b1 n44
b0 n41
b1 n39
b100 n36
#195
b0 n9
b0 n27
b0 n39
#200
b00010100 n22
b0000 n18
b0100 n17
b000000000000000010100 n10
b1 n9
b1 n34
b1 n32
b1 n27
b100 n26
b0 n45
b0 n44
b1 n39
b000 n36
#205
b0 n9
b0 n27
b0 n39
#210
b00010101 n22
b1111 n18
b0101 n17
b000000000000000010101 n10
b1 n9
b0 n34
b0 n32
b0 n29
b1 n27
b000 n26
b1 n39
#215
b0 n9
b0 n27
b0 n39
#220
b00010110 n22
b1110 n18
b0110 n17
b1 n14
b000000000000000010110 n10
b1 n9
b1 n27
b1 n39
b1 n37
#225
b0 n9
b0 n27
b0 n39
#230
b00010111 n22
b1101 n18
b0111 n17
b1 n15
b000000000000000010111 n10
b1 n9
b1 n27
b1 n23
b1 n39
b001 n38
#235
b0 n9
b0 n27
b0 n39
#240
b00011000 n22
b1100 n18
b1000 n17
b000000000000000011000 n10
b1 n9
b1 n27
b001 n24
b1 n46
b1 n44
b1 n39
b011 n38
#245
b0 n9
b0 n27
b0 n39
#250
b00011001 n22
b1011 n18
b1001 n17
b1 n13
b000000000000000011001 n10
b1 n9
b1 n33
b1 n32
b1 n29
b1 n27
b011 n24
b0 n46
b0 n44
b1 n41
b1 n39
b111 n38
b1 n35
#255
b0 n9
b0 n27
b0 n39
#260
b00011010 n22
b1010 n18
b1010 n17
b1 n16
b000000000000000011010 n10
b1 n9
b0 n33
b0 n32
b1 n27
b1 n25
b111 n24
b1 n39
b001 n36
#265
b0 n9
b0 n27
b0 n39
#270
b00011011 n22
b1001 n18
b1011 n17
b000000000000000011011 n10
b1 n9
b1 n27
b001 n26
b1 n45
b1 n44
b0 n41
b1 n39
b011 n36
#275
b0 n9
b0 n27
b0 n39
#280
b00011100 n22
b1000 n18
b1100 n17
b000000000000000011100 n10
b1 n9
b1 n34
b1 n32
b1 n27
b011 n26
b0 n45
b0 n44
b1 n39
b111 n36
#285
b0 n9
b0 n27
b0 n39
#290
b00011101 n22
b0111 n18
b1101 n17
b000000000000000011101 n10
b1 n9
b0 n34
b0 n32
b0 n29
b1 n27
b111 n26
b1 n39
#295
b0 n9
b0 n27
b0 n39
#300
b00011110 n22
b0110 n18
b1110 n17
b0 n14
b000000000000000011110 n10
b1 n9
b1 n27
b1 n39
b0 n37
#305
b0 n9
b0 n27
b0 n39
#310
b00011111 n22
b0101 n18
b1111 n17
b0 n15
b000000000000000011111 n10
b1 n9
b1 n27
b0 n23
b1 n39
b110 n38
#315
b0 n9
b0 n27
b0 n39
#320
b00100000 n22
b0100 n18
b0000 n17
b000000000000000100000 n10
b1 n9
b1 n27
b110 n24
b1 n46
b1 n44
b1 n39
b100 n38
#325
b0 n9
b0 n27
b0 n39
#330
b00100001 n22
b0011 n18
b0001 n17
b0 n13
b000000000000000100001 n10
b1 n9
b1 n33
b1 n32
b1 n29
b1 n27
b100 n24
b0 n46
b0 n44
b1 n41
b1 n39
b000 n38
b0 n35
#335
b0 n9
b0 n27
b0 n39
#340
b00100010 n22
b0010 n18
b0010 n17
b0 n16
b000000000000000100010 n10
b1 n9
b0 n33
b0 n32
b1 n27
b0 n25
b000 n24
b1 n39
b110 n36
#345
b0 n9
b0 n27
b0 n39
#350
b00100011 n22
b0001 n18
b0011 n17
b000000000000000100011 n10
b1 n9
b1 n27
b110 n26
b1 n45
b1 n44
b0 n41
b1 n39
b100 n36
#355
b0 n9
b0 n27
b0 n39
#360
b00100100 n22
b0000 n18
b0100 n17
b000000000000000100100 n10
b1 n9
b1 n34
b1 n32
b1 n27
b100 n26
b0 n45
b0 n44
b1 n39
b000 n36
#365
b0 n9
b0 n27
b0 n39
#370
b00100101 n22
b1111 n18
b0101 n17
b000000000000000100101 n10
b1 n9
b0 n34
b0 n32
b0 n29
b1 n27
b000 n26
b1 n39
#375
b0 n9
b0 n27
b0 n39
#380
b00100110 n22
b1110 n18
b0110 n17
b1 n14
b000000000000000100110 n10
b1 n9
b1 n27
b1 n39
b1 n37
#385
b0 n9
b0 n27
b0 n39
#390
b00100111 n22
b1101 n18
b0111 n17
b1 n15
b000000000000000100111 n10
b1 n9
b1 n27
b1 n23
b1 n39
b001 n38
#395
b0 n9
b0 n27
b0 n39
#400
b00101000 n22
b1100 n18
b1000 n17
b000000000000000101000 n10
b1 n9
b1 n27
b001 n24
b1 n46
b1 n44
b1 n39
b011 n38
#405
b0 n9
b0 n27
b0 n39
#410
b00101001 n22
b1011 n18
b1001 n17
b1 n13
b000000000000000101001 n10
b1 n9
b1 n33
b1 n32
b1 n29
b1 n27
b011 n24
b0 n46
b0 n44
b1 n41
b1 n39
b111 n38
b1 n35
#415
b0 n9
b0 n27
b0 n39
#420
b00101010 n22
b1010 n18
b1010 n17
b1 n16
b000000000000000101010 n10
b1 n9
b0 n33
b0 n32
b1 n27
b1 n25
b111 n24
b1 n39
b001 n36
#425
b0 n9
b0 n27
b0 n39
#430
b00101011 n22
b1001 n18
b1011 n17
b000000000000000101011 n10
b1 n9
b1 n27
b001 n26
b1 n45
b1 n44
b0 n41
b1 n39
b011 n36
#435
b0 n9
b0 n27
b0 n39
#440
b00101100 n22
b1000 n18
b1100 n17
b000000000000000101100 n10
b1 n9
b1 n34
b1 n32
b1 n27
b011 n26
b0 n45
b0 n44
b1 n39
b111 n36
#445
b0 n9
b0 n27
b0 n39
#450
b00101101 n22
b0111 n18
b1101 n17
b000000000000000101101 n10
b1 n9
b0 n34
b0 n32
b0 n29
b1 n27
b111 n26
b1 n39
#455
b0 n9
b0 n27
b0 n39
#460
b00101110 n22
b0110 n18
b1110 n17
b0 n14
b000000000000000101110 n10
b1 n9
b1 n27
b1 n39
b0 n37
#465
b0 n9
b0 n27
b0 n39
#470
b00101111 n22
b0101 n18
b1111 n17
b0 n15
b000000000000000101111 n10
b1 n9
b1 n27
b0 n23
b1 n39
b110 n38
#475
b0 n9
b0 n27
b0 n39
#480
b00110000 n22
b0100 n18
b0000 n17
b000000000000000110000 n10
b1 n9
b1 n27
b110 n24
b1 n46
b1 n44
b1 n39
b100 n38
#485
b0 n9
b0 n27
b0 n39
#490
b00110001 n22
b0011 n18
b0001 n17
b0 n13
b000000000000000110001 n10
b1 n9
b1 n33
b1 n32
b1 n29
b1 n27
b100 n24
b0 n46
b0 n44
b1 n41
b1 n39
b000 n38
b0 n35
#495
b0 n9
b0 n27
b0 n39
#500
b00110010 n22
b0010 n18
b0010 n17
b0 n16
b000000000000000110010 n10
b1 n9
b0 n33
b0 n32
b1 n27
b0 n25
b000 n24
b1 n39
b110 n36
#505
b0 n9
b0 n27
b0 n39
#510
b00110011 n22
b0001 n18
b0011 n17
b000000000000000110011 n10
b1 n9
b1 n27
b110 n26
b1 n45
b1 n44
b0 n41
b1 n39
b100 n36
#515
b0 n9
b0 n27
b0 n39
#520
b00110100 n22
b0000 n18
b0100 n17
b000000000000000110100 n10
b1 n9
b1 n34
b1 n32
b1 n27
b100 n26
b0 n45
b0 n44
b1 n39
b000 n36
#525
b0 n9
b0 n27
b0 n39
#530
b00110101 n22
b1111 n18
b0101 n17
b000000000000000110101 n10
b1 n9
b0 n34
b0 n32
b0 n29
b1 n27
b000 n26
b1 n39
#535
b0 n9
b0 n27
b0 n39
#540
b00110110 n22
b1110 n18
b0110 n17
b1 n14
b000000000000000110110 n10
b1 n9
b1 n27
b1 n39
b1 n37
#545
b0 n9
b0 n27
b0 n39
#550
b00110111 n22
b1101 n18
b0111 n17
b1 n15
b000000000000000110111 n10
b1 n9
b1 n27
b1 n23
b1 n39
b001 n38
#555
b0 n9
b0 n27
b0 n39
#560
b00111000 n22
b1100 n18
b1000 n17
b000000000000000111000 n10
b1 n9
b1 n27
b001 n24
b1 n46
b1 n44
b1 n39
b011 n38
#565
b0 n9
b0 n27
b0 n39
#570
b00111001 n22
b1011 n18
b1001 n17
b1 n13
b000000000000000111001 n10
b1 n9
b1 n33
b1 n32
b1 n29
b1 n27
b011 n24
b0 n46
b0 n44
b1 n41
b1 n39
b111 n38
b1 n35
#575
b0 n9
b0 n27
b0 n39
#580
b00111010 n22
b1010 n18
b1010 n17
b1 n16
b000000000000000111010 n10
b1 n9
b0 n33
b0 n32
b1 n27
b1 n25
b111 n24
b1 n39
b001 n36
#585
b0 n9
b0 n27
b0 n39
#590
b00111011 n22
b1001 n18
b1011 n17
b000000000000000111011 n10
b1 n9
b1 n27
b001 n26
b1 n45
b1 n44
b0 n41
b1 n39
b011 n36
#595
b0 n9
b0 n27
b0 n39
#600
b00111100 n22
b1000 n18
b1100 n17
b000000000000000111100 n10
b1 n9
b1 n34
b1 n32
b1 n27
b011 n26
b0 n45
b0 n44
b1 n39
b111 n36
#605
b0 n9
b0 n27
b0 n39
#610
b00111101 n22
b0111 n18
b1101 n17
b000000000000000111101 n10
b1 n9
b0 n34
b0 n32
b0 n29
b1 n27
b111 n26
b1 n39
#615
b0 n9
b0 n27
b0 n39
#620
b00111110 n22
b0110 n18
b1110 n17
b0 n14
b000000000000000111110 n10
b1 n9
b1 n27
b1 n39
b0 n37
#625
b0 n9
b0 n27
b0 n39
#630
b00111111 n22
b0101 n18
b1111 n17
b0 n15
b000000000000000111111 n10
b1 n9
b1 n27
b0 n23
b1 n39
b110 n38
#635
b0 n9
b0 n27
b0 n39
#640
b01000000 n22
b0100 n18
b0000 n17
b000000000000001000000 n10
b1 n9
b1 n27
b110 n24
b1 n46
b1 n44
b1 n39
b100 n38
#645
b0 n9
b0 n27
b0 n39
#650
b01000001 n22
b0011 n18
b0001 n17
b0 n13
b000000000000001000001 n10
b1 n9
b1 n33
b1 n32
b1 n29
b1 n27
b100 n24
b0 n46
b0 n44
b1 n41
b1 n39
b000 n38
b0 n35
#655
b0 n9
b0 n27
b0 n39
#660
b01000010 n22
b0010 n18
b0010 n17
b0 n16
b000000000000001000010 n10
b1 n9
b0 n33
b0 n32
b1 n27
b0 n25
b000 n24
b1 n39
b110 n36
#665
b0 n9
b0 n27
b0 n39
#670
b01000011 n22
b0001 n18
b0011 n17
b000000000000001000011 n10
b1 n9
b1 n27
b110 n26
b1 n45
b1 n44
b0 n41
b1 n39
b100 n36
#675
b0 n9
b0 n27
b0 n39
#680
b01000100 n22
b0000 n18
b0100 n17
b000000000000001000100 n10
b1 n9
b1 n34
b1 n32
b1 n27
b100 n26
b0 n45
b0 n44
b1 n39
b000 n36
#685
b0 n9
b0 n27
b0 n39
#690
b01000101 n22
b1111 n18
b0101 n17
b000000000000001000101 n10
b1 n9
b0 n34
b0 n32
b0 n29
b1 n27
b000 n26
b1 n39
#695
b0 n9
b0 n27
b0 n39
#700
b01000110 n22
b1110 n18
b0110 n17
b1 n14
b000000000000001000110 n10
b1 n9
b1 n27
b1 n39
b1 n37
#705
b0 n9
b0 n27
b0 n39
#710
b01000111 n22
b1101 n18
b0111 n17
b1 n15
b000000000000001000111 n10
b1 n9
b1 n27
b1 n23
b1 n39
b001 n38
#715
b0 n9
b0 n27
b0 n39
#720
b01001000 n22
b1100 n18
b1000 n17
b000000000000001001000 n10
b1 n9
b1 n27
b001 n24
b1 n46
b1 n44
b1 n39
b011 n38
#725
b0 n9
b0 n27
b0 n39
#730
b01001001 n22
b1011 n18
b1001 n17
b1 n13
b000000000000001001001 n10
b1 n9
b1 n33
b1 n32
b1 n29
b1 n27
b011 n24
b0 n46
b0 n44
b1 n41
b1 n39
b111 n38
b1 n35
#735
b0 n9
b0 n27
b0 n39
#740
b01001010 n22
b1010 n18
b1010 n17
b1 n16
b000000000000001001010 n10
b1 n9
b0 n33
b0 n32
b1 n27
b1 n25
b111 n24
b1 n39
b001 n36
#745
b0 n9
b0 n27
b0 n39
#750
b01001011 n22
b1001 n18
b1011 n17
b000000000000001001011 n10
b1 n9
b1 n27
b001 n26
b1 n45
b1 n44
b0 n41
b1 n39
b011 n36
#755
b0 n9
b0 n27
b0 n39
#760
b01001100 n22
b1000 n18
b1100 n17
b000000000000001001100 n10
b1 n9
b1 n34
b1 n32
b1 n27
b011 n26
b0 n45
b0 n44
b1 n39
b111 n36
#765
b0 n9
b0 n27
b0 n39
#770
b01001101 n22
b0111 n18
b1101 n17
b000000000000001001101 n10
b1 n9
b0 n34
b0 n32
b0 n29
b1 n27
b111 n26
b1 n39
#775
b0 n9
b0 n27
b0 n39
#780
b01001110 n22
b0110 n18
b1110 n17
b0 n14
b000000000000001001110 n10
b1 n9
b1 n27
b1 n39
b0 n37
#785
b0 n9
b0 n27
b0 n39
#790
b01001111 n22
b0101 n18
b1111 n17
b0 n15
b000000000000001001111 n10
b1 n9
b1 n27
b0 n23
b1 n39
b110 n38
#795
b0 n9
b0 n27
b0 n39
#800
b01010000 n22
b0100 n18
b0000 n17
b000000000000001010000 n10
b1 n9
b1 n27
b110 n24
b1 n46
b1 n44
b1 n39
b100 n38
#805
b0 n9
b0 n27
b0 n39
#810
b01010001 n22
b0011 n18
b0001 n17
b0 n13
b000000000000001010001 n10
b1 n9
b1 n33
b1 n32
b1 n29
b1 n27
b100 n24
b0 n46
b0 n44
b1 n41
b1 n39
b000 n38
b0 n35
#815
b0 n9
b0 n27
b0 n39
#820
b01010010 n22
b0010 n18
b0010 n17
b0 n16
b000000000000001010010 n10
b1 n9
b0 n33
b0 n32
b1 n27
b0 n25
b000 n24
b1 n39
b110 n36
#825
b0 n9
b0 n27
b0 n39
#830
b01010011 n22
b0001 n18
b0011 n17
b000000000000001010011 n10
b1 n9
b1 n27
b110 n26
b1 n45
b1 n44
b0 n41
b1 n39
b100 n36
#835
b0 n9
b0 n27
b0 n39
#840
b01010100 n22
b0000 n18
b0100 n17
b000000000000001010100 n10
b1 n9
b1 n34
b1 n32
b1 n27
b100 n26
b0 n45
b0 n44
b1 n39
b000 n36
#845
b0 n9
b0 n27
b0 n39
#850
b01010101 n22
b1111 n18
b0101 n17
b000000000000001010101 n10
b1 n9
b0 n34
b0 n32
b0 n29
b1 n27
b000 n26
b1 n39
#855
b0 n9
b0 n27
b0 n39
#860
b01010110 n22
b1110 n18
b0110 n17
b1 n14
b000000000000001010110 n10
b1 n9
b1 n27
b1 n39
b1 n37
#865
b0 n9
b0 n27
b0 n39
#870
b01010111 n22
b1101 n18
b0111 n17
b1 n15
b000000000000001010111 n10
b1 n9
b1 n27
b1 n23
b1 n39
b001 n38
#875
b0 n9
b0 n27
b0 n39
#880
b01011000 n22
b1100 n18
b1000 n17
b000000000000001011000 n10
b1 n9
b1 n27
b001 n24
b1 n46
b1 n44
b1 n39
b011 n38
#885
b0 n9
b0 n27
b0 n39
#890
b01011001 n22
b1011 n18
b1001 n17
b1 n13
b000000000000001011001 n10
b1 n9
b1 n33
b1 n32
b1 n29
b1 n27
b011 n24
b0 n46
b0 n44
b1 n41
b1 n39
b111 n38
b1 n35
#895
b0 n9
b0 n27
b0 n39
#900
b01011010 n22
b1010 n18
b1010 n17
b1 n16
b000000000000001011010 n10
b1 n9
b0 n33
b0 n32
b1 n27
b1 n25
b111 n24
b1 n39
b001 n36
#905
b0 n9
b0 n27
b0 n39
#910
b01011011 n22
b1001 n18
b1011 n17
b000000000000001011011 n10
b1 n9
b1 n27
b001 n26
b1 n45
b1 n44
b0 n41
b1 n39
b011 n36
#915
b0 n9
b0 n27
b0 n39
#920
b01011100 n22
b1000 n18
b1100 n17
b000000000000001011100 n10
b1 n9
b1 n34
b1 n32
b1 n27
b011 n26
b0 n45
b0 n44
b1 n39
b111 n36
#925
b0 n9
b0 n27
b0 n39
#930
b01011101 n22
b0111 n18
b1101 n17
b000000000000001011101 n10
b1 n9
b0 n34
b0 n32
b0 n29
b1 n27
b111 n26
b1 n39
#935
b0 n9
b0 n27
b0 n39
#940
b01011110 n22
b0110 n18
b1110 n17
b0 n14
b000000000000001011110 n10
b1 n9
b1 n27
b1 n39
b0 n37
#945
b0 n9
b0 n27
b0 n39
#950
b01011111 n22
b0101 n18
b1111 n17
b0 n15
b000000000000001011111 n10
b1 n9
b1 n27
b0 n23
b1 n39
b110 n38
#955
b0 n9
b0 n27
b0 n39
#960
b01100000 n22
b0100 n18
b0000 n17
b000000000000001100000 n10
b1 n9
b1 n27
b110 n24
b1 n46
b1 n44
b1 n39
b100 n38
#965
b0 n9
b0 n27
b0 n39
#970
b01100001 n22
b0011 n18
b0001 n17
b0 n13
b000000000000001100001 n10
b1 n9
b1 n33
b1 n32
b1 n29
b1 n27
b100 n24
b0 n46
b0 n44
b1 n41
b1 n39
b000 n38
b0 n35
#975
b0 n9
b0 n27
b0 n39
#980
b01100010 n22
b0010 n18
b0010 n17
b0 n16
b000000000000001100010 n10
b1 n9
b0 n33
b0 n32
b1 n27
b0 n25
b000 n24
b1 n39
b110 n36
#985
b0 n9
b0 n27
b0 n39
#990
b01100011 n22
b0001 n18
b0011 n17
b000000000000001100011 n10
b1 n9
b1 n27
b110 n26
b1 n45
b1 n44
b0 n41
b1 n39
b100 n36
#995
b0 n9
b0 n27
b0 n39
#1000
b01100100 n22
b0000 n18
b0100 n17
b000000000000001100100 n10
b1 n9
b1 n34
b1 n32
b1 n27
b100 n26
b0 n45
b0 n44
b1 n39
b000 n36
#1005
b0 n9
b0 n27
b0 n39
#1010
b01100101 n22
b1111 n18
b0101 n17
b000000000000001100101 n10
b1 n9
b0 n34
b0 n32
b0 n29
b1 n27
b000 n26
b1 n39
#1015
b0 n9
b0 n27
b0 n39
#1020
b01100110 n22
b1110 n18
b0110 n17
b1 n14
b000000000000001100110 n10
b1 n9
b1 n27
b1 n39
b1 n37
#1025
b0 n9
b0 n27
b0 n39
#1030
b01100111 n22
b1101 n18
b0111 n17
b1 n15
b000000000000001100111 n10
b1 n9
b1 n27
b1 n23
b1 n39
b001 n38
#1035
b0 n9
b0 n27
b0 n39
#1040
b01101000 n22
b1100 n18
b1000 n17
b000000000000001101000 n10
b1 n9
b1 n27
b001 n24
b1 n46
b1 n44
b1 n39
b011 n38
#1045
b0 n9
b0 n27
b0 n39
#1050
b01101001 n22
b1011 n18
b1001 n17
b1 n13
b000000000000001101001 n10
b1 n9
b1 n33
b1 n32
b1 n29
b1 n27
b011 n24
b0 n46
b0 n44
b1 n41
b1 n39
b111 n38
b1 n35
#1055
b0 n9
b0 n27
b0 n39
#1060
b01101010 n22
b1010 n18
b1010 n17
b1 n16
b000000000000001101010 n10
b1 n9
b0 n33
b0 n32
b1 n27
b1 n25
b111 n24
b1 n39
b001 n36
#1065
b0 n9
b0 n27
b0 n39
#1070
b01101011 n22
b1001 n18
b1011 n17
b000000000000001101011 n10
b1 n9
b1 n27
b001 n26
b1 n45
b1 n44
b0 n41
b1 n39
b011 n36
#1075
b0 n9
b0 n27
b0 n39
