pos_count.v
/*  UltiCores -- IP Cores for Mechatronic Control Systems
 *
 *  Copyright (C) 2019 UltiMachine <info@ultimachine.com>
 *
 *  Permission to use, copy, modify, and/or distribute this software for any
 *  purpose with or without fee is hereby granted, provided that the above
 *  copyright notice and this permission notice appear in all copies.
 *
 *  THE SOFTWARE IS PROVIDED "AS IS" AND THE AUTHOR DISCLAIMS ALL WARRANTIES
 *  WITH REGARD TO THIS SOFTWARE INCLUDING ALL IMPLIED WARRANTIES OF
 *  MERCHANTABILITY AND FITNESS. IN NO EVENT SHALL THE AUTHOR BE LIABLE FOR
 *  ANY SPECIAL, DIRECT, INDIRECT, OR CONSEQUENTIAL DAMAGES OR ANY DAMAGES
 *  WHATSOEVER RESULTING FROM LOSS OF USE, DATA OR PROFITS, WHETHER IN AN
 *  ACTION OF CONTRACT, NEGLIGENCE OR OTHER TORTIOUS ACTION, ARISING OUT OF
 *  OR IN CONNECTION WITH THE USE OR PERFORMANCE OF THIS SOFTWARE.
 */

/* quad_enc.v
 * Quadrature decoder inspired by https://www.fpga4fun.com/QuadratureDecoder.html
 * Converted to 32 bit. Added reset and fault logic. Changed some names to fit us.
 */

module pos_counter(
  input resetn,
  input clk,
  input step,
  input dir,
//  input step_on_edge, // If True, count on every step/dir change -Not implemented
  input step_active_high,  // If true, count when change to high
  input invert_dir, // Changes count up/down direction
  output reg [31:0] count
  );

//  wire faultn;

  reg [2:0] step_buf;  // Hold sample before compare for stability
  reg [1:0] dir_buf;
//  reg active_edge; //

  wire pos_edge = (step_buf[2:1] == 2'b01);
  wire neg_edge = (step_buf[2:1] == 2'b10);
  
//  wire edge_seen = step_buf[1] ^ step_buf[2];  // Did step change during last clock period?
	
//  wire active_edge = ((step & step_active_high) | (step ~| step_active_high)); // Is the edge we are triggering on the correct edge?
//  wire stepped = edge_seen & step_buf[1]; // If the edge was the right polarity
  wire direction = dir_buf[1] ^ invert_dir;  //Direction determined by buffered input and config register

  always @(posedge clk) begin
    step_buf <= {step_buf[1:0], step};  //Shift new step in. Last 2 samples shift to bits 2 and 1 
    dir_buf <= {dir_buf[0], dir};  //Shift new dir in
//    if (step_active_high)	
//	  active_edge <= step;
//    else 
//	  active_edge <= ~step;

    if (!resetn) begin
      count <= 0;  //reset count
    end
    else begin
      if (step_active_high) begin
        if (pos_edge) begin
          if (direction) 
            count <= count + 1;
          else 
            count <= count - 1;
        end
      end
      else begin
        if (neg_edge) begin
          if (direction) 
            count <= count + 1;
          else 
            count <= count - 1;
        end
      end
    end
  end
endmodule

quad_enc.v
/*  UltiCores -- IP Cores for Mechatronic Control Systems
 *
 *  Copyright (C) 2019 UltiMachine <info@ultimachine.com>
 *
 *  Permission to use, copy, modify, and/or distribute this software for any
 *  purpose with or without fee is hereby granted, provided that the above
 *  copyright notice and this permission notice appear in all copies.
 *
 *  THE SOFTWARE IS PROVIDED "AS IS" AND THE AUTHOR DISCLAIMS ALL WARRANTIES
 *  WITH REGARD TO THIS SOFTWARE INCLUDING ALL IMPLIED WARRANTIES OF
 *  MERCHANTABILITY AND FITNESS. IN NO EVENT SHALL THE AUTHOR BE LIABLE FOR
 *  ANY SPECIAL, DIRECT, INDIRECT, OR CONSEQUENTIAL DAMAGES OR ANY DAMAGES
 *  WHATSOEVER RESULTING FROM LOSS OF USE, DATA OR PROFITS, WHETHER IN AN
 *  ACTION OF CONTRACT, NEGLIGENCE OR OTHER TORTIOUS ACTION, ARISING OUT OF
 *  OR IN CONNECTION WITH THE USE OR PERFORMANCE OF THIS SOFTWARE.
 */

/* quad_enc.v
 * Quadrature decoder inspired by https://www.fpga4fun.com/QuadratureDecoder.html
 * Converted to 32 bit. Added reset and fault logic. Changed some names to fit us.
 */

module quad_enc(
  input resetn,
  input clk,
  input a,
  input b,
  output reg faultn,
  output reg [31:0] count
  );

//  wire faultn;

  reg [2:0] a_stable, b_stable;  //Hold sample before compare for stability

  wire step_a = a_stable[1] ^ a_stable[2];  //Step if a changed
  wire step_b = b_stable[1] ^ b_stable[2];  //Step if b changed
  wire step = step_a ^ step_b;  //Step if a xor b stepped
  wire direction = a_stable[1] ^ b_stable[2];  //Direction determined by comparing current sample to last

  always @(posedge clk) begin
    a_stable <= {a_stable[1:0], a};  //Shift new a in. Last 2 samples shift to bits 2 and 1 
    b_stable <= {b_stable[1:0], b};  //Shift new b in

    if (!resetn) begin
      count <= 0;  //reset count
      faultn <= 1; //reset faultn
    end
    else begin
      if (step_a && step_b)  //We do not know direction if both inputs triggered on single clock
        faultn <= 0;
      if (step) begin
        if (direction) 
          count <= count + 1;
        else 
          count <= count - 1;
      end
    end
  end
endmodule

ulticore.v
/*
 *
 *  UltiCores -- IP Cores for Mechatronic Control Systems
 *
 *  Copyright (C) 2019 UltiMachine <info@ultimachine.com>
 *
 *  Permission to use, copy, modify, and/or distribute this software for any
 *  purpose with or without fee is hereby granted, provided that the above
 *  copyright notice and this permission notice appear in all copies.
 *
 *  THE SOFTWARE IS PROVIDED "AS IS" AND THE AUTHOR DISCLAIMS ALL WARRANTIES
 *  WITH REGARD TO THIS SOFTWARE INCLUDING ALL IMPLIED WARRANTIES OF
 *  MERCHANTABILITY AND FITNESS. IN NO EVENT SHALL THE AUTHOR BE LIABLE FOR
 *  ANY SPECIAL, DIRECT, INDIRECT, OR CONSEQUENTIAL DAMAGES OR ANY DAMAGES
 *  WHATSOEVER RESULTING FROM LOSS OF USE, DATA OR PROFITS, WHETHER IN AN
 *  ACTION OF CONTRACT, NEGLIGENCE OR OTHER TORTIOUS ACTION, ARISING OUT OF
 *  OR IN CONNECTION WITH THE USE OR PERFORMANCE OF THIS SOFTWARE.
 *
 */

// Parts lifted from picorv32 - regfile

//`include "quad_enc.v"
`timescale 1ns/100ps

module ulticore(
  input clk, 
  input enc1a,
  input enc1b,
  input enc2a,
  input enc2b,
  input enc3a,
  input enc3b,
  input enc4a,
  input enc4b,
  input enc5a,
  input enc5b,
  input enc6a,
  input enc6b,
  input enc7a,
  input enc7b,
  input enc8a,
  input enc8b,
  input step1,
  input step2,
  input step3,
  input step4,
  input step5,
  input step6,
  input step7,
  input step8,
  input dir1,
  input dir2,
  input dir3,
  input dir4,
  input dir5,
  input dir6,
  input dir7,
  input dir8,
  output LED0,
  output LED1,
  output LED2,
  output LED3,
  output LED4,
  output LED5,
  output LED6,
  output LED7,
  output faultn,
  input [7:0] invert_dir,
  input [7:0] step_active_high
  );

//  reg enc1a, enc1b, enc2a, enc2b;
  wire [31:0] enc_count1, enc_count2, enc_count3, enc_count4, enc_count5, enc_count6, enc_count7, enc_count8;
  wire [31:0] pos_count1, pos_count2, pos_count3, pos_count4, pos_count5, pos_count6, pos_count7, pos_count8;
//  reg resetn;
  wire resetn;
  reg [7:0] resetn_counter = 0;
  wire faultn;
  wire [7:0] fault;

  assign faultn = &fault;

  assign resetn = &resetn_counter;

  always @(posedge clk) begin
    if (!resetn) resetn_counter <= resetn_counter +1;
  end

  quad_enc quad1(.resetn(resetn), .clk(clk), .a(enc1a), .b(enc1b), .count(enc_count1), .faultn(fault[0]));
  quad_enc quad2(.resetn(resetn), .clk(clk), .a(enc2a), .b(enc2b), .count(enc_count2), .faultn(fault[1]));
  quad_enc quad3(.resetn(resetn), .clk(clk), .a(enc3a), .b(enc3b), .count(enc_count3), .faultn(fault[2]));
  quad_enc quad4(.resetn(resetn), .clk(clk), .a(enc4a), .b(enc4b), .count(enc_count4), .faultn(fault[3]));
  quad_enc quad5(.resetn(resetn), .clk(clk), .a(enc5a), .b(enc5b), .count(enc_count5), .faultn(fault[4]));
  quad_enc quad6(.resetn(resetn), .clk(clk), .a(enc6a), .b(enc6b), .count(enc_count6), .faultn(fault[5]));
  quad_enc quad7(.resetn(resetn), .clk(clk), .a(enc7a), .b(enc7b), .count(enc_count7), .faultn(fault[6]));
  quad_enc quad8(.resetn(resetn), .clk(clk), .a(enc8a), .b(enc8b), .count(enc_count8), .faultn(fault[7]));

  pos_counter pos_counter1(.resetn(resetn), .clk(clk), .step(step1), .dir(dir1), .step_active_high(step_active_high[0]), .invert_dir(invert_dir[0]), .count(pos_count1));
  pos_counter pos_counter2(.resetn(resetn), .clk(clk), .step(step2), .dir(dir2), .step_active_high(step_active_high[1]), .invert_dir(invert_dir[1]), .count(pos_count2));
  pos_counter pos_counter3(.resetn(resetn), .clk(clk), .step(step3), .dir(dir3), .step_active_high(step_active_high[2]), .invert_dir(invert_dir[2]), .count(pos_count3));
  pos_counter pos_counter4(.resetn(resetn), .clk(clk), .step(step4), .dir(dir4), .step_active_high(step_active_high[3]), .invert_dir(invert_dir[3]), .count(pos_count4));
  pos_counter pos_counter5(.resetn(resetn), .clk(clk), .step(step5), .dir(dir5), .step_active_high(step_active_high[4]), .invert_dir(invert_dir[4]), .count(pos_count5));
  pos_counter pos_counter6(.resetn(resetn), .clk(clk), .step(step6), .dir(dir6), .step_active_high(step_active_high[5]), .invert_dir(invert_dir[5]), .count(pos_count6));
  pos_counter pos_counter7(.resetn(resetn), .clk(clk), .step(step7), .dir(dir7), .step_active_high(step_active_high[6]), .invert_dir(invert_dir[6]), .count(pos_count7));
  pos_counter pos_counter8(.resetn(resetn), .clk(clk), .step(step8), .dir(dir8), .step_active_high(step_active_high[7]), .invert_dir(invert_dir[7]), .count(pos_count8));


  assign {LED0} = enc_count1[3:3] ^ pos_count1[3:3];
  assign {LED1} = enc_count2[3:3] ^ pos_count2[3:3];
  assign {LED2} = enc_count3[3:3] ^ pos_count3[3:3];
  assign {LED3} = enc_count4[3:3] ^ pos_count4[3:3];
  assign {LED4} = enc_count5[3:3] ^ pos_count5[3:3];
  assign {LED5} = enc_count6[3:3] ^ pos_count6[3:3];
  assign {LED6} = enc_count7[3:3] ^ pos_count7[3:3];
  assign {LED7} = enc_count8[3:3] ^ pos_count8[3:3];

endmodule

ulticore_tb.v
`timescale 1ns/100ps


module testbench();

  reg clk;
  reg enc1a;
  reg enc1b;
  reg enc2a;
  reg enc2b;
  reg enc3a;
  reg enc3b;
  reg enc4a;
  reg enc4b;
  reg enc5a;
  reg enc5b;
  reg enc6a;
  reg enc6b;
  reg enc7a;
  reg enc7b;
  reg enc8a;
  reg enc8b;
  reg step1;
  reg step2;
  reg step3;
  reg step4;
  reg step5;
  reg step6;
  reg step7;
  reg step8;
  reg dir1;
  reg dir2;
  reg dir3;
  reg dir4;
  reg dir5;
  reg dir6;
  reg dir7;
  reg dir8;
  wire [7:0]led;
  wire faultn;
//  wire [31:0] enc_count1, enc_count2, enc_count3, enc_count4, enc_count5, enc_count6, enc_count7, enc_count8;
  reg [3:0] resetn_tb_counter = 0;
//  reg [7:0] fault;
  reg [20:0] cnt = 0;
  reg [7:0] invert_dir = 0;
  reg [7:0] step_active_high = 256;

// Clock stimulation
  always #5 clk = (clk === 1'b0);

  initial begin
    $dumpfile("testbench.vcd");
    $dumpvars(0, testbench);

    repeat (10) begin
      repeat (256) @(posedge clk);
      $display("+256 cycles");
    end
    $finish;
  end

// Debug output

  always @(faultn) begin
    #1 $display("%b", faultn);
  end

  always @(led) begin
    #1 $display("%b", led);
  end

// Reset TB timer
  assign resetn_tb = &resetn_tb_counter;

  always @(posedge clk) begin
    if (!resetn_tb) resetn_tb_counter <= resetn_tb_counter +1;
  end


// Encoder Stimulation

  reg [3:0] enccntA = 0;
  reg [3:0] enccntB = 4;

  always @(posedge clk) begin
    if(!resetn_tb) begin
      cnt <= 0;
//      fault[7:0] <= 'b11111111;
    end
    else begin
//      faultn <= &fault;
      cnt <= cnt + 1;
      if (cnt <= 20'h110) begin
        enccntA <= enccntA + 1;
        enc1a <= enccntA[3];
        enccntB <= enccntB - 1;
        enc1b <= enccntB[3];
        enc2a <= enc1b;
        enc2b <= enc1a;
        enc3a <= enc1a;
        enc3b <= enc1b;
        enc4a <= enc1b;
        enc4b <= enc1a;
        enc5a <= enc1a;
        enc5b <= enc1b;
        enc6a <= enc1b;
        enc6b <= enc1a;
        enc7a <= enc1a;
        enc7b <= enc1b;
        enc8a <= enc1b;
        enc8b <= enc1a;
        step1 <= enccntA[3];
        step2 <= enccntA[3];
        step3 <= enccntA[3];
        step4 <= enccntA[3];
        step5 <= enccntA[3];
        step6 <= enccntA[3];
        step7 <= enccntA[3];
        step8 <= enccntA[3];
        dir1 <= 0;
        dir2 <= 0;
        dir3 <= 0;
        dir4 <= 0;
        dir5 <= 0;
        dir6 <= 0;
        dir7 <= 0;
        dir8 <= 0;
      end
      else begin
//        cnt <=0;
        enccntA <= enccntA + 1;
        enc1a <= enccntA[3];
        enccntB <= enccntB - 1;
        enc1b <= enccntB[3];
        enc2a <= ~enc2a;  //Inject fault in encoder 2
        enc2b <= ~enc2b;
        enc3a <= enc1b; //Reverse
        enc3b <= enc1a;
        enc4a <= enc1b;
        enc4b <= enc1a;
        enc5a <= enc1a;
        enc5b <= enc1b;
        enc6a <= enc1b;
        enc6b <= enc1a;
        enc7a <= enc1a;
        enc7b <= enc1b;
        enc8a <= enc1b;
        enc8b <= enc1a;
        step1 <= enccntA[3]; //Step opposite direction
        step2 <= enccntA[3];
        step3 <= enccntA[3];
        step4 <= enccntA[3];
        step5 <= enccntA[3];
        step6 <= enccntA[3];
        step7 <= enccntA[3];
        step8 <= enccntA[3];
        dir1 <= 1;
        dir2 <= 1;
        dir3 <= 1;
        dir4 <= 1;
        dir5 <= 1;
        dir6 <= 1;
        dir7 <= 1;
        dir8 <= 1;
      end
    end
  end


// UUT

  ulticore uut (
    .clk  (clk  ),
    .enc1a (enc1a ),
    .enc1b (enc1b ),
    .enc2a (enc2a ),
    .enc2b (enc2b ),
    .enc3a (enc3a ),
    .enc3b (enc3b ),
    .enc4a (enc4a ),
    .enc4b (enc4b ),
    .enc5a (enc5a ),
    .enc5b (enc5b ),
    .enc6a (enc6a ),
    .enc6b (enc6b ),
    .enc7a (enc7a ),
    .enc7b (enc7b ),
    .enc8a (enc8a ),
    .enc8b (enc8b ),
    .LED0 (led[0] ),
    .LED1 (led[1] ),
    .LED2 (led[2] ),
    .LED3 (led[3] ),
    .LED4 (led[4] ),
    .LED5 (led[5] ),
    .LED6 (led[6] ),
    .LED7 (led[7] ),
    .invert_dir (0),
    .step_active_high (256),
    .step1 (step1),
    .step2 (step2),
    .step3 (step3),
    .step4 (step4),
    .step5 (step5),
    .step6 (step6),
    .step7 (step7),
    .step8 (step8),
    .dir1 (dir1),
    .dir2 (dir2),
    .dir3 (dir3),
    .dir4 (dir4),
    .dir5 (dir5),
    .dir6 (dir6),
    .dir7 (dir7),
    .dir8 (dir8),
    .faultn(faultn)
  );
endmodule

testbench.vcd
$date
	Mon Nov  4 21:48:02 2019
$end
$version
	Icarus Verilog
$end
$timescale
	100ps
$end
$scope module testbench $end
$var wire 1 ! resetn_tb $end
$var wire 8 " led [7:0] $end
$var wire 1 # faultn $end
$var reg 1 $ clk $end
$var reg 21 % cnt [20:0] $end
$var reg 1 & dir1 $end
$var reg 1 ' dir2 $end
$var reg 1 ( dir3 $end
$var reg 1 ) dir4 $end
$var reg 1 * dir5 $end
$var reg 1 + dir6 $end
$var reg 1 , dir7 $end
$var reg 1 - dir8 $end
$var reg 1 . enc1a $end
$var reg 1 / enc1b $end
$var reg 1 0 enc2a $end
$var reg 1 1 enc2b $end
$var reg 1 2 enc3a $end
$var reg 1 3 enc3b $end
$var reg 1 4 enc4a $end
$var reg 1 5 enc4b $end
$var reg 1 6 enc5a $end
$var reg 1 7 enc5b $end
$var reg 1 8 enc6a $end
$var reg 1 9 enc6b $end
$var reg 1 : enc7a $end
$var reg 1 ; enc7b $end
$var reg 1 < enc8a $end
$var reg 1 = enc8b $end
$var reg 4 > enccntA [3:0] $end
$var reg 4 ? enccntB [3:0] $end
$var reg 8 @ invert_dir [7:0] $end
$var reg 4 A resetn_tb_counter [3:0] $end
$var reg 1 B step1 $end
$var reg 1 C step2 $end
$var reg 1 D step3 $end
$var reg 1 E step4 $end
$var reg 1 F step5 $end
$var reg 1 G step6 $end
$var reg 1 H step7 $end
$var reg 1 I step8 $end
$var reg 8 J step_active_high [7:0] $end
$scope module uut $end
$var wire 1 $ clk $end
$var wire 1 & dir1 $end
$var wire 1 ' dir2 $end
$var wire 1 ( dir3 $end
$var wire 1 ) dir4 $end
$var wire 1 * dir5 $end
$var wire 1 + dir6 $end
$var wire 1 , dir7 $end
$var wire 1 - dir8 $end
$var wire 1 . enc1a $end
$var wire 1 / enc1b $end
$var wire 1 0 enc2a $end
$var wire 1 1 enc2b $end
$var wire 1 2 enc3a $end
$var wire 1 3 enc3b $end
$var wire 1 4 enc4a $end
$var wire 1 5 enc4b $end
$var wire 1 6 enc5a $end
$var wire 1 7 enc5b $end
$var wire 1 8 enc6a $end
$var wire 1 9 enc6b $end
$var wire 1 : enc7a $end
$var wire 1 ; enc7b $end
$var wire 1 < enc8a $end
$var wire 1 = enc8b $end
$var wire 8 K invert_dir [7:0] $end
$var wire 1 B step1 $end
$var wire 1 C step2 $end
$var wire 1 D step3 $end
$var wire 1 E step4 $end
$var wire 1 F step5 $end
$var wire 1 G step6 $end
$var wire 1 H step7 $end
$var wire 1 I step8 $end
$var wire 8 L step_active_high [7:0] $end
$var wire 1 M resetn $end
$var wire 32 N pos_count8 [31:0] $end
$var wire 32 O pos_count7 [31:0] $end
$var wire 32 P pos_count6 [31:0] $end
$var wire 32 Q pos_count5 [31:0] $end
$var wire 32 R pos_count4 [31:0] $end
$var wire 32 S pos_count3 [31:0] $end
$var wire 32 T pos_count2 [31:0] $end
$var wire 32 U pos_count1 [31:0] $end
$var wire 1 # faultn $end
$var wire 8 V fault [7:0] $end
$var wire 32 W enc_count8 [31:0] $end
$var wire 32 X enc_count7 [31:0] $end
$var wire 32 Y enc_count6 [31:0] $end
$var wire 32 Z enc_count5 [31:0] $end
$var wire 32 [ enc_count4 [31:0] $end
$var wire 32 \ enc_count3 [31:0] $end
$var wire 32 ] enc_count2 [31:0] $end
$var wire 32 ^ enc_count1 [31:0] $end
$var wire 1 _ LED7 $end
$var wire 1 ` LED6 $end
$var wire 1 a LED5 $end
$var wire 1 b LED4 $end
$var wire 1 c LED3 $end
$var wire 1 d LED2 $end
$var wire 1 e LED1 $end
$var wire 1 f LED0 $end
$var reg 8 g resetn_counter [7:0] $end
$scope module pos_counter1 $end
$var wire 1 $ clk $end
$var wire 1 & dir $end
$var wire 1 h direction $end
$var wire 1 i invert_dir $end
$var wire 1 M resetn $end
$var wire 1 B step $end
$var wire 1 j step_active_high $end
$var wire 1 k pos_edge $end
$var wire 1 l neg_edge $end
$var reg 32 m count [31:0] $end
$var reg 2 n dir_buf [1:0] $end
$var reg 3 o step_buf [2:0] $end
$upscope $end
$scope module pos_counter2 $end
$var wire 1 $ clk $end
$var wire 1 ' dir $end
$var wire 1 p direction $end
$var wire 1 q invert_dir $end
$var wire 1 M resetn $end
$var wire 1 C step $end
$var wire 1 r step_active_high $end
$var wire 1 s pos_edge $end
$var wire 1 t neg_edge $end
$var reg 32 u count [31:0] $end
$var reg 2 v dir_buf [1:0] $end
$var reg 3 w step_buf [2:0] $end
$upscope $end
$scope module pos_counter3 $end
$var wire 1 $ clk $end
$var wire 1 ( dir $end
$var wire 1 x direction $end
$var wire 1 y invert_dir $end
$var wire 1 M resetn $end
$var wire 1 D step $end
$var wire 1 z step_active_high $end
$var wire 1 { pos_edge $end
$var wire 1 | neg_edge $end
$var reg 32 } count [31:0] $end
$var reg 2 ~ dir_buf [1:0] $end
$var reg 3 !" step_buf [2:0] $end
$upscope $end
$scope module pos_counter4 $end
$var wire 1 $ clk $end
$var wire 1 ) dir $end
$var wire 1 "" direction $end
$var wire 1 #" invert_dir $end
$var wire 1 M resetn $end
$var wire 1 E step $end
$var wire 1 $" step_active_high $end
$var wire 1 %" pos_edge $end
$var wire 1 &" neg_edge $end
$var reg 32 '" count [31:0] $end
$var reg 2 (" dir_buf [1:0] $end
$var reg 3 )" step_buf [2:0] $end
$upscope $end
$scope module pos_counter5 $end
$var wire 1 $ clk $end
$var wire 1 * dir $end
$var wire 1 *" direction $end
$var wire 1 +" invert_dir $end
$var wire 1 M resetn $end
$var wire 1 F step $end
$var wire 1 ," step_active_high $end
$var wire 1 -" pos_edge $end
$var wire 1 ." neg_edge $end
$var reg 32 /" count [31:0] $end
$var reg 2 0" dir_buf [1:0] $end
$var reg 3 1" step_buf [2:0] $end
$upscope $end
$scope module pos_counter6 $end
$var wire 1 $ clk $end
$var wire 1 + dir $end
$var wire 1 2" direction $end
$var wire 1 3" invert_dir $end
$var wire 1 M resetn $end
$var wire 1 G step $end
$var wire 1 4" step_active_high $end
$var wire 1 5" pos_edge $end
$var wire 1 6" neg_edge $end
$var reg 32 7" count [31:0] $end
$var reg 2 8" dir_buf [1:0] $end
$var reg 3 9" step_buf [2:0] $end
$upscope $end
$scope module pos_counter7 $end
$var wire 1 $ clk $end
$var wire 1 , dir $end
$var wire 1 :" direction $end
$var wire 1 ;" invert_dir $end
$var wire 1 M resetn $end
$var wire 1 H step $end
$var wire 1 <" step_active_high $end
$var wire 1 =" pos_edge $end
$var wire 1 >" neg_edge $end
$var reg 32 ?" count [31:0] $end
$var reg 2 @" dir_buf [1:0] $end
$var reg 3 A" step_buf [2:0] $end
$upscope $end
$scope module pos_counter8 $end
$var wire 1 $ clk $end
$var wire 1 - dir $end
$var wire 1 B" direction $end
$var wire 1 C" invert_dir $end
$var wire 1 M resetn $end
$var wire 1 I step $end
$var wire 1 D" step_active_high $end
$var wire 1 E" pos_edge $end
$var wire 1 F" neg_edge $end
$var reg 32 G" count [31:0] $end
$var reg 2 H" dir_buf [1:0] $end
$var reg 3 I" step_buf [2:0] $end
$upscope $end
$scope module quad1 $end
$var wire 1 . a $end
$var wire 1 / b $end
$var wire 1 $ clk $end
$var wire 1 J" direction $end
$var wire 1 M resetn $end
$var wire 1 K" step $end
$var wire 1 L" step_a $end
$var wire 1 M" step_b $end
$var reg 3 N" a_stable [2:0] $end
$var reg 3 O" b_stable [2:0] $end
$var reg 32 P" count [31:0] $end
$var reg 1 Q" faultn $end
$upscope $end
$scope module quad2 $end
$var wire 1 0 a $end
$var wire 1 1 b $end
$var wire 1 $ clk $end
$var wire 1 R" direction $end
$var wire 1 M resetn $end
$var wire 1 S" step $end
$var wire 1 T" step_a $end
$var wire 1 U" step_b $end
$var reg 3 V" a_stable [2:0] $end
$var reg 3 W" b_stable [2:0] $end
$var reg 32 X" count [31:0] $end
$var reg 1 Y" faultn $end
$upscope $end
$scope module quad3 $end
$var wire 1 2 a $end
$var wire 1 3 b $end
$var wire 1 $ clk $end
$var wire 1 Z" direction $end
$var wire 1 M resetn $end
$var wire 1 [" step $end
$var wire 1 \" step_a $end
$var wire 1 ]" step_b $end
$var reg 3 ^" a_stable [2:0] $end
$var reg 3 _" b_stable [2:0] $end
$var reg 32 `" count [31:0] $end
$var reg 1 a" faultn $end
$upscope $end
$scope module quad4 $end
$var wire 1 4 a $end
$var wire 1 5 b $end
$var wire 1 $ clk $end
$var wire 1 b" direction $end
$var wire 1 M resetn $end
$var wire 1 c" step $end
$var wire 1 d" step_a $end
$var wire 1 e" step_b $end
$var reg 3 f" a_stable [2:0] $end
$var reg 3 g" b_stable [2:0] $end
$var reg 32 h" count [31:0] $end
$var reg 1 i" faultn $end
$upscope $end
$scope module quad5 $end
$var wire 1 6 a $end
$var wire 1 7 b $end
$var wire 1 $ clk $end
$var wire 1 j" direction $end
$var wire 1 M resetn $end
$var wire 1 k" step $end
$var wire 1 l" step_a $end
$var wire 1 m" step_b $end
$var reg 3 n" a_stable [2:0] $end
$var reg 3 o" b_stable [2:0] $end
$var reg 32 p" count [31:0] $end
$var reg 1 q" faultn $end
$upscope $end
$scope module quad6 $end
$var wire 1 8 a $end
$var wire 1 9 b $end
$var wire 1 $ clk $end
$var wire 1 r" direction $end
$var wire 1 M resetn $end
$var wire 1 s" step $end
$var wire 1 t" step_a $end
$var wire 1 u" step_b $end
$var reg 3 v" a_stable [2:0] $end
$var reg 3 w" b_stable [2:0] $end
$var reg 32 x" count [31:0] $end
$var reg 1 y" faultn $end
$upscope $end
$scope module quad7 $end
$var wire 1 : a $end
$var wire 1 ; b $end
$var wire 1 $ clk $end
$var wire 1 z" direction $end
$var wire 1 M resetn $end
$var wire 1 {" step $end
$var wire 1 |" step_a $end
$var wire 1 }" step_b $end
$var reg 3 ~" a_stable [2:0] $end
$var reg 3 !# b_stable [2:0] $end
$var reg 32 "# count [31:0] $end
$var reg 1 ## faultn $end
$upscope $end
$scope module quad8 $end
$var wire 1 < a $end
$var wire 1 = b $end
$var wire 1 $ clk $end
$var wire 1 $# direction $end
$var wire 1 M resetn $end
$var wire 1 %# step $end
$var wire 1 &# step_a $end
$var wire 1 '# step_b $end
$var reg 3 (# a_stable [2:0] $end
$var reg 3 )# b_stable [2:0] $end
$var reg 32 *# count [31:0] $end
$var reg 1 +# faultn $end
$upscope $end
$upscope $end
$upscope $end
$enddefinitions $end
#0
$dumpvars
x+#
bx *#
bx )#
bx (#
x'#
x&#
x%#
x$#
x##
bx "#
bx !#
bx ~"
x}"
x|"
x{"
xz"
xy"
bx x"
bx w"
bx v"
xu"
xt"
xs"
xr"
xq"
bx p"
bx o"
bx n"
xm"
xl"
xk"
xj"
xi"
bx h"
bx g"
bx f"
xe"
xd"
xc"
xb"
xa"
bx `"
bx _"
bx ^"
x]"
x\"
x["
xZ"
xY"
bx X"
bx W"
bx V"
xU"
xT"
xS"
xR"
xQ"
bx P"
bx O"
bx N"
xM"
xL"
xK"
xJ"
bx I"
bx H"
bx G"
xF"
xE"
0D"
0C"
xB"
bx A"
bx @"
bx ?"
x>"
x="
0<"
0;"
x:"
bx 9"
bx 8"
bx 7"
x6"
x5"
04"
03"
x2"
bx 1"
bx 0"
bx /"
x."
x-"
0,"
0+"
x*"
bx )"
bx ("
bx '"
x&"
x%"
0$"
0#"
x""
bx !"
bx ~
bx }
x|
x{
0z
0y
xx
bx w
bx v
bx u
xt
xs
0r
0q
xp
bx o
bx n
bx m
xl
xk
0j
0i
xh
b0 g
xf
xe
xd
xc
xb
xa
x`
x_
bx ^
bx ]
bx \
bx [
bx Z
bx Y
bx X
bx W
bx V
bx U
bx T
bx S
bx R
bx Q
bx P
bx O
bx N
0M
b0 L
b0 K
b0 J
xI
xH
xG
xF
xE
xD
xC
xB
b0 A
b0 @
b100 ?
b0 >
x=
x<
x;
x:
x9
x8
x7
x6
x5
x4
x3
x2
x1
x0
x/
x.
x-
x,
x+
x*
x)
x(
x'
x&
b0 %
x$
x#
bx "
0!
$end
#50
0$
#100
0f
0e
0d
0c
0b
0a
0`
b0 "
0_
1#
1Q"
b0 ^
b0 P"
1Y"
b0 ]
b0 X"
1a"
b0 \
b0 `"
1i"
b0 [
b0 h"
1q"
b0 Z
b0 p"
1y"
b0 Y
b0 x"
1##
b0 X
b0 "#
b11111111 V
1+#
b0 W
b0 *#
b0 U
b0 m
b0 T
b0 u
b0 S
b0 }
b0 R
b0 '"
b0 Q
b0 /"
b0 P
b0 7"
b0 O
b0 ?"
b0 N
b0 G"
b1 g
b1 A
1$
#150
0$
#200
b10 A
b10 g
1$
#250
0$
#300
b11 g
b11 A
1$
#350
0$
#400
b100 A
b100 g
1$
#450
0$
#500
b101 g
b101 A
1$
#550
0$
#600
b110 A
b110 g
1$
#650
0$
#700
b111 g
b111 A
1$
#750
0$
#800
b1000 A
b1000 g
1$
#850
0$
#900
b1001 g
b1001 A
1$
#950
0$
#1000
b1010 A
b1010 g
1$
#1050
0$
#1100
b1011 g
b1011 A
1$
#1150
0$
#1200
b1100 A
b1100 g
1$
#1250
0$
#1300
b1101 g
b1101 A
1$
#1350
0$
#1400
b1110 A
b1110 g
1$
#1450
0$
#1500
b1111 g
1!
b1111 A
1$
#1550
0$
#1600
0-
0,
0+
0*
0)
0(
0'
0&
0I
0H
0G
0F
0E
0D
0C
0B
0/
b11 ?
0.
b1 >
b1 %
b10000 g
1$
#1650
0$
#1700
bx0 O"
bx0 N"
bx0 n
bx0 o
bx0 v
bx0 w
bx0 ~
bx0 !"
bx0 ("
bx0 )"
bx0 0"
bx0 1"
bx0 8"
bx0 9"
bx0 @"
bx0 A"
bx0 H"
bx0 I"
b10001 g
0=
0<
0;
0:
09
08
07
06
05
04
03
02
01
00
b10 ?
b10 >
b10 %
1$
#1750
0$
#1800
0B"
0:"
02"
0*"
0""
0x
0p
0h
0E"
0="
05"
0-"
0%"
0{
0s
0k
b1 ?
b11 >
b11 %
b10010 g
b0 H"
bx00 I"
b0 @"
bx00 A"
b0 8"
bx00 9"
b0 0"
bx00 1"
b0 ("
bx00 )"
b0 ~
bx00 !"
b0 v
bx00 w
b0 n
bx00 o
bx0 )#
bx0 (#
bx0 !#
bx0 ~"
bx0 w"
bx0 v"
bx0 o"
bx0 n"
bx0 g"
bx0 f"
bx0 _"
bx0 ^"
bx0 W"
bx0 V"
bx00 O"
bx00 N"
1$
#1850
0$
#1900
0K"
0M"
0J"
0L"
0l
0t
0|
0&"
0."
06"
0>"
0F"
b0 O"
b0 N"
bx00 W"
bx00 V"
bx00 _"
bx00 ^"
bx00 g"
bx00 f"
bx00 o"
bx00 n"
bx00 w"
bx00 v"
bx00 !#
bx00 ~"
bx00 )#
bx00 (#
b0 o
b0 w
b0 !"
b0 )"
b0 1"
b0 9"
b0 A"
b0 I"
b10011 g
b0 ?
b100 >
b100 %
1$
#1950
0$
