quad_enc.v
/*  UltiCores -- IP Cores for Mechatronic Control Systems
 *
 *  Copyright (C) 2019 UltiMachine <info@ultimachine.com>
 *
 *  Permission to use, copy, modify, and/or distribute this software for any
 *  purpose with or without fee is hereby granted, provided that the above
 *  copyright notice and this permission notice appear in all copies.
 *
 *  THE SOFTWARE IS PROVIDED "AS IS" AND THE AUTHOR DISCLAIMS ALL WARRANTIES
 *  WITH REGARD TO THIS SOFTWARE INCLUDING ALL IMPLIED WARRANTIES OF
 *  MERCHANTABILITY AND FITNESS. IN NO EVENT SHALL THE AUTHOR BE LIABLE FOR
 *  ANY SPECIAL, DIRECT, INDIRECT, OR CONSEQUENTIAL DAMAGES OR ANY DAMAGES
 *  WHATSOEVER RESULTING FROM LOSS OF USE, DATA OR PROFITS, WHETHER IN AN
 *  ACTION OF CONTRACT, NEGLIGENCE OR OTHER TORTIOUS ACTION, ARISING OUT OF
 *  OR IN CONNECTION WITH THE USE OR PERFORMANCE OF THIS SOFTWARE.
 */

/* quad_enc.v
 * Quadrature decoder inspired by https://www.fpga4fun.com/QuadratureDecoder.html
 * Converted to 32 bit. Added reset and fault logic. Changed some names to fit us.
 */

module quad_enc(
  input resetn,
  input clk,
  input a,
  input b,
  output reg faultn,
  output reg [31:0] count
  );

//  wire faultn;

  reg [2:0] a_stable, b_stable;  //Hold sample before compare for stability

  wire step_a = a_stable[1] ^ a_stable[2];  //Step if a changed
  wire step_b = b_stable[1] ^ b_stable[2];  //Step if b changed
  wire step = step_a ^ step_b;  //Step if a xor b stepped
  wire direction = a_stable[1] ^ b_stable[2];  //Direction determined by comparing current sample to last

  always @(posedge clk) begin
    a_stable <= {a_stable[1:0], a};  //Shift new a in. Last 2 samples shift to bits 2 and 1 
    b_stable <= {b_stable[1:0], b};  //Shift new b in

    if (!resetn) begin
      count <= 0;  //reset count
      faultn <= 1; //reset faultn
    end
    else begin
      if (step_a && step_b)  //We do not know direction if both inputs triggered on single clock
        faultn <= 0;
      if (step) begin
        if (direction) 
          count <= count + 1;
        else 
          count <= count - 1;
      end
    end
  end
endmodule

ulticore.v
/*
 *
 *  UltiCores -- IP Cores for Mechatronic Control Systems
 *
 *  Copyright (C) 2019 UltiMachine <info@ultimachine.com>
 *
 *  Permission to use, copy, modify, and/or distribute this software for any
 *  purpose with or without fee is hereby granted, provided that the above
 *  copyright notice and this permission notice appear in all copies.
 *
 *  THE SOFTWARE IS PROVIDED "AS IS" AND THE AUTHOR DISCLAIMS ALL WARRANTIES
 *  WITH REGARD TO THIS SOFTWARE INCLUDING ALL IMPLIED WARRANTIES OF
 *  MERCHANTABILITY AND FITNESS. IN NO EVENT SHALL THE AUTHOR BE LIABLE FOR
 *  ANY SPECIAL, DIRECT, INDIRECT, OR CONSEQUENTIAL DAMAGES OR ANY DAMAGES
 *  WHATSOEVER RESULTING FROM LOSS OF USE, DATA OR PROFITS, WHETHER IN AN
 *  ACTION OF CONTRACT, NEGLIGENCE OR OTHER TORTIOUS ACTION, ARISING OUT OF
 *  OR IN CONNECTION WITH THE USE OR PERFORMANCE OF THIS SOFTWARE.
 *
 */

//`include "quad_enc.v"
`timescale 1ns/100ps

module ulticore(
  input clk, 
  input enc1a,
  input enc1b,
  input enc2a,
  input enc2b,
  input enc3a,
  input enc3b,
  input enc4a,
  input enc4b,
  input enc5a,
  input enc5b,
  input enc6a,
  input enc6b,
  input enc7a,
  input enc7b,
  input enc8a,
  input enc8b,
  output LED0,
  output LED1,
  output LED2,
  output LED3,
  output LED4,
  output LED5,
  output LED6,
  output LED7,
  output faultn
  );

//  reg enc1a, enc1b, enc2a, enc2b;
  wire [31:0] count1, count2, count3, count4, count5, count6, count7, count8;
//  reg resetn;
  wire resetn;
  reg [7:0] resetn_counter = 0;
  wire faultn;
  wire [7:0] fault;

  assign resetn = &resetn_counter;

  always @(posedge clk) begin
    if (!resetn) resetn_counter <= resetn_counter +1;
  end

  quad_enc quad1(.resetn(resetn), .clk(clk), .a(enc1a), .b(enc1b), .count(count1), .faultn(fault[0]));
  quad_enc quad2(.resetn(resetn), .clk(clk), .a(enc2a), .b(enc2b), .count(count2), .faultn(fault[1]));
  quad_enc quad3(.resetn(resetn), .clk(clk), .a(enc3a), .b(enc3b), .count(count3), .faultn(fault[2]));
  quad_enc quad4(.resetn(resetn), .clk(clk), .a(enc4a), .b(enc4b), .count(count4), .faultn(fault[3]));
  quad_enc quad5(.resetn(resetn), .clk(clk), .a(enc5a), .b(enc5b), .count(count5), .faultn(fault[4]));
  quad_enc quad6(.resetn(resetn), .clk(clk), .a(enc6a), .b(enc6b), .count(count6), .faultn(fault[5]));
  quad_enc quad7(.resetn(resetn), .clk(clk), .a(enc7a), .b(enc7b), .count(count7), .faultn(fault[6]));
  quad_enc quad8(.resetn(resetn), .clk(clk), .a(enc8a), .b(enc8b), .count(count8), .faultn(fault[7]));


  assign {LED0} = count1[3:3];
  assign {LED1} = count2[3:3];
  assign {LED2} = count3[3:3];
  assign {LED3} = count4[3:3];
  assign {LED4} = count5[3:3];
  assign {LED5} = count6[3:3];
  assign {LED6} = count7[3:3];
  assign {LED7} = count8[3:3];
//  assign {LED4, LED5, LED6, LED7} = count2[3:0];


endmodule

ulticore_tb.v
module testbench();

  reg clk;
  reg enc1a;
  reg enc1b;
  reg enc2a;
  reg enc2b;
  reg enc3a;
  reg enc3b;
  reg enc4a;
  reg enc4b;
  reg enc5a;
  reg enc5b;
  reg enc6a;
  reg enc6b;
  reg enc7a;
  reg enc7b;
  reg enc8a;
  reg enc8b;
  wire [7:0]led;
  reg faultn;
  wire [31:0] count1, count2, count3, count4, count5, count6, count7, count8;
//  wire resetn;
//  wire resetn_tb;
  reg [7:0] resetn_tb_counter = 0;
  reg [7:0] fault;
  reg [20:0] cnt;

/*
// Reset
  assign resetn_tb = &resetn_tb_counter;

  always @(posedge clk) begin
    if (!resetn) resetn_counter <= resetn_counter +1;
  end
*/

// Clock stimulation
  always #5 clk = (clk === 1'b0);

  initial begin
    $dumpfile("testbench.vcd");
    $dumpvars(0, testbench);

    repeat (10) begin
      repeat (256) @(posedge clk);
      $display("+256 cycles");
    end
    $finish;
  end

// Debug output

  always @(fault) begin
    #1 $display("%b", fault);
  end

  always @(led) begin
    #1 $display("%b", led);
  end

// Reset TB timer
  assign resetn_tb = &resetn_tb_counter;

  always @(posedge clk) begin
    if (!resetn_tb) resetn_tb_counter <= resetn_tb_counter +1;
  end


// Encoder Stimulation

  reg [3:0] enccntA = 0;
  reg [3:0] enccntB = 4;

  always @(posedge clk) begin
    if(!resetn_tb) begin
      cnt <= 0;
      fault[7:0] <= 'b11111111;
    end
    faultn <= &fault;
    cnt <= cnt + 1;
    if (cnt <= 20'h90) begin
      enccntA <= enccntA + 1;
      enc1a <= enccntA[3];
      enccntB <= enccntB - 1;
      enc1b <= enccntB[3];
      enc2a <= enc1b;
      enc2b <= enc1a;
      enc3a <= enc1a;
      enc3b <= enc1b;
      enc4a <= enc1b;
      enc4b <= enc1a;
      enc5a <= enc1a;
      enc5b <= enc1b;
      enc6a <= enc1b;
      enc6b <= enc1a;
      enc7a <= enc1a;
      enc7b <= enc1b;
      enc8a <= enc1b;
      enc8b <= enc1a;
    end
    else begin
      cnt <=0;
      enc2a <= ~enc2a;  //Inject fault in encoder 2
      enc2b <= ~enc2b;
      enc7a <= ~enc7a;
      enc7b <= ~enc7b;
    end

  end


// UUT

  ulticore uut (
    .clk  (clk  ),
    .enc1a (enc1a ),
    .enc1b (enc1b ),
    .enc2a (enc2a ),
    .enc2b (enc2b ),
    .enc3a (enc3a ),
    .enc3b (enc3b ),
    .enc4a (enc4a ),
    .enc4b (enc4b ),
    .enc5a (enc5a ),
    .enc5b (enc5b ),
    .enc6a (enc6a ),
    .enc6b (enc6b ),
    .enc7a (enc7a ),
    .enc7b (enc7b ),
    .enc8a (enc8a ),
    .enc8b (enc8b ),
    .LED0 (led[0] ),
    .LED1 (led[1] ),
    .LED2 (led[2] ),
    .LED3 (led[3] ),
    .LED4 (led[4] ),
    .LED5 (led[5] ),
    .LED6 (led[6] ),
    .LED7 (led[7] )
  );
endmodule

testbench.vcd
$date
	Sun Nov  3 11:20:39 2019
$end
$version
	Icarus Verilog
$end
$timescale
	100ps
$end
$scope module testbench $end
$var wire 1 ! resetn_tb $end
$var wire 8 " led [7:0] $end
$var reg 1 # clk $end
$var reg 21 $ cnt [20:0] $end
$var reg 1 % enc1a $end
$var reg 1 & enc1b $end
$var reg 1 ' enc2a $end
$var reg 1 ( enc2b $end
$var reg 1 ) enc3a $end
$var reg 1 * enc3b $end
$var reg 1 + enc4a $end
$var reg 1 , enc4b $end
$var reg 1 - enc5a $end
$var reg 1 . enc5b $end
$var reg 1 / enc6a $end
$var reg 1 0 enc6b $end
$var reg 1 1 enc7a $end
$var reg 1 2 enc7b $end
$var reg 1 3 enc8a $end
$var reg 1 4 enc8b $end
$var reg 4 5 enccntA [3:0] $end
$var reg 4 6 enccntB [3:0] $end
$var reg 8 7 fault [7:0] $end
$var reg 1 8 faultn $end
$var reg 8 9 resetn_tb_counter [7:0] $end
$scope module uut $end
$var wire 1 # clk $end
$var wire 1 % enc1a $end
$var wire 1 & enc1b $end
$var wire 1 ' enc2a $end
$var wire 1 ( enc2b $end
$var wire 1 ) enc3a $end
$var wire 1 * enc3b $end
$var wire 1 + enc4a $end
$var wire 1 , enc4b $end
$var wire 1 - enc5a $end
$var wire 1 . enc5b $end
$var wire 1 / enc6a $end
$var wire 1 0 enc6b $end
$var wire 1 1 enc7a $end
$var wire 1 2 enc7b $end
$var wire 1 3 enc8a $end
$var wire 1 4 enc8b $end
$var wire 1 : faultn $end
$var wire 1 ; resetn $end
$var wire 8 < fault [7:0] $end
$var wire 32 = count8 [31:0] $end
$var wire 32 > count7 [31:0] $end
$var wire 32 ? count6 [31:0] $end
$var wire 32 @ count5 [31:0] $end
$var wire 32 A count4 [31:0] $end
$var wire 32 B count3 [31:0] $end
$var wire 32 C count2 [31:0] $end
$var wire 32 D count1 [31:0] $end
$var wire 1 E LED7 $end
$var wire 1 F LED6 $end
$var wire 1 G LED5 $end
$var wire 1 H LED4 $end
$var wire 1 I LED3 $end
$var wire 1 J LED2 $end
$var wire 1 K LED1 $end
$var wire 1 L LED0 $end
$var reg 8 M resetn_counter [7:0] $end
$scope module quad1 $end
$var wire 1 % a $end
$var wire 1 & b $end
$var wire 1 # clk $end
$var wire 1 N direction $end
$var wire 1 ; resetn $end
$var wire 1 O step $end
$var wire 1 P step_a $end
$var wire 1 Q step_b $end
$var reg 3 R a_stable [2:0] $end
$var reg 3 S b_stable [2:0] $end
$var reg 32 T count [31:0] $end
$var reg 1 U faultn $end
$upscope $end
$scope module quad2 $end
$var wire 1 ' a $end
$var wire 1 ( b $end
$var wire 1 # clk $end
$var wire 1 V direction $end
$var wire 1 ; resetn $end
$var wire 1 W step $end
$var wire 1 X step_a $end
$var wire 1 Y step_b $end
$var reg 3 Z a_stable [2:0] $end
$var reg 3 [ b_stable [2:0] $end
$var reg 32 \ count [31:0] $end
$var reg 1 ] faultn $end
$upscope $end
$scope module quad3 $end
$var wire 1 ) a $end
$var wire 1 * b $end
$var wire 1 # clk $end
$var wire 1 ^ direction $end
$var wire 1 ; resetn $end
$var wire 1 _ step $end
$var wire 1 ` step_a $end
$var wire 1 a step_b $end
$var reg 3 b a_stable [2:0] $end
$var reg 3 c b_stable [2:0] $end
$var reg 32 d count [31:0] $end
$var reg 1 e faultn $end
$upscope $end
$scope module quad4 $end
$var wire 1 + a $end
$var wire 1 , b $end
$var wire 1 # clk $end
$var wire 1 f direction $end
$var wire 1 ; resetn $end
$var wire 1 g step $end
$var wire 1 h step_a $end
$var wire 1 i step_b $end
$var reg 3 j a_stable [2:0] $end
$var reg 3 k b_stable [2:0] $end
$var reg 32 l count [31:0] $end
$var reg 1 m faultn $end
$upscope $end
$scope module quad5 $end
$var wire 1 - a $end
$var wire 1 . b $end
$var wire 1 # clk $end
$var wire 1 n direction $end
$var wire 1 ; resetn $end
$var wire 1 o step $end
$var wire 1 p step_a $end
$var wire 1 q step_b $end
$var reg 3 r a_stable [2:0] $end
$var reg 3 s b_stable [2:0] $end
$var reg 32 t count [31:0] $end
$var reg 1 u faultn $end
$upscope $end
$scope module quad6 $end
$var wire 1 / a $end
$var wire 1 0 b $end
$var wire 1 # clk $end
$var wire 1 v direction $end
$var wire 1 ; resetn $end
$var wire 1 w step $end
$var wire 1 x step_a $end
$var wire 1 y step_b $end
$var reg 3 z a_stable [2:0] $end
$var reg 3 { b_stable [2:0] $end
$var reg 32 | count [31:0] $end
$var reg 1 } faultn $end
$upscope $end
$scope module quad7 $end
$var wire 1 1 a $end
$var wire 1 2 b $end
$var wire 1 # clk $end
$var wire 1 ~ direction $end
$var wire 1 ; resetn $end
$var wire 1 !" step $end
$var wire 1 "" step_a $end
$var wire 1 #" step_b $end
$var reg 3 $" a_stable [2:0] $end
$var reg 3 %" b_stable [2:0] $end
$var reg 32 &" count [31:0] $end
$var reg 1 '" faultn $end
$upscope $end
$scope module quad8 $end
$var wire 1 3 a $end
$var wire 1 4 b $end
$var wire 1 # clk $end
$var wire 1 (" direction $end
$var wire 1 ; resetn $end
$var wire 1 )" step $end
$var wire 1 *" step_a $end
$var wire 1 +" step_b $end
$var reg 3 ," a_stable [2:0] $end
$var reg 3 -" b_stable [2:0] $end
$var reg 32 ." count [31:0] $end
$var reg 1 /" faultn $end
$upscope $end
$upscope $end
$upscope $end
$enddefinitions $end
#0
$dumpvars
x/"
bx ."
bx -"
bx ,"
x+"
x*"
x)"
x("
x'"
bx &"
bx %"
bx $"
x#"
x""
x!"
x~
x}
bx |
bx {
bx z
xy
xx
xw
xv
xu
bx t
bx s
bx r
xq
xp
xo
xn
xm
bx l
bx k
bx j
xi
xh
xg
xf
xe
bx d
bx c
bx b
xa
x`
x_
x^
x]
bx \
bx [
bx Z
xY
xX
xW
xV
xU
bx T
bx S
bx R
xQ
xP
xO
xN
b0 M
xL
xK
xJ
xI
xH
xG
xF
xE
bx D
bx C
bx B
bx A
bx @
bx ?
bx >
bx =
bx <
0;
z:
b0 9
x8
bx 7
b100 6
b0 5
x4
x3
x2
x1
x0
x/
x.
x-
x,
x+
x*
x)
x(
x'
x&
x%
bx $
x#
bx "
0!
$end
#50000000000
0#
#100000000000
0L
0K
0J
0I
0H
0G
0F
b0 "
0E
1U
b0 D
b0 T
1]
b0 C
b0 \
1e
b0 B
b0 d
1m
b0 A
b0 l
1u
b0 @
b0 t
1}
b0 ?
b0 |
1'"
b0 >
b0 &"
b11111111 <
1/"
b0 =
b0 ."
b1 M
b1 9
b11111111 7
b0 $
1#
#150000000000
0#
#200000000000
0&
b11 6
0%
b1 5
b1 $
18
b10 9
b10 M
1#
#250000000000
0#
#300000000000
bx0 S
bx0 R
b11 M
b11 9
04
03
02
01
00
0/
0.
0-
0,
0+
0*
0)
0(
0'
b10 6
b10 5
b10 $
1#
#350000000000
0#
#400000000000
b1 6
b11 5
b11 $
b100 9
b100 M
bx0 -"
bx0 ,"
bx0 %"
bx0 $"
bx0 {
bx0 z
bx0 s
bx0 r
bx0 k
bx0 j
bx0 c
bx0 b
bx0 [
bx0 Z
bx00 S
bx00 R
1#
#450000000000
0#
#500000000000
0O
0Q
0N
0P
b0 S
b0 R
bx00 [
bx00 Z
bx00 c
bx00 b
bx00 k
bx00 j
bx00 s
bx00 r
bx00 {
bx00 z
bx00 %"
bx00 $"
bx00 -"
bx00 ,"
b101 M
b101 9
b0 6
b100 5
b100 $
1#
#550000000000
0#
#600000000000
0)"
0!"
0w
0o
0g
0_
0W
0+"
0("
0*"
0#"
0~
0""
0y
0v
0x
0q
0n
0p
0i
0f
0h
0a
0^
0`
0Y
0V
0X
b1111 6
b101 5
b101 $
b110 9
b110 M
b0 -"
b0 ,"
b0 %"
b0 $"
b0 {
b0 z
b0 s
b0 r
b0 k
b0 j
b0 c
b0 b
b0 [
b0 Z
1#
#650000000000
0#
#700000000000
b111 M
b111 9
1&
b1110 6
b110 5
b110 $
1#
#750000000000
0#
#800000000000
13
12
1/
1.
1+
1*
1'
b1101 6
b111 5
b111 $
b1000 9
b1000 M
b1 S
1#
#850000000000
0#
#900000000000
1O
1Q
b11 S
b1 Z
b1 c
b1 j
b1 s
b1 z
b1 %"
b1 ,"
b1001 M
b1001 9
b1100 6
b1000 5
b1000 $
1#
#950000000000
0#
#1000000000000
1)"
1!"
1w
1o
1g
1_
1W
0O
1*"
1("
1#"
1x
1v
1q
1h
1f
1a
1X
1V
0Q
1N
b1011 6
1%
b1001 5
b1001 $
b1010 9
b1010 M
b11 ,"
b11 %"
b11 z
b11 s
b11 j
b11 c
b11 Z
b111 S
1#
#1050000000000
0#
#1100000000000
0W
0_
0g
0o
0w
0!"
0)"
0X
0a
1^
0h
0q
1n
0x
0#"
1~
0*"
b1 R
b111 Z
b111 c
b111 j
b111 s
b111 z
b111 %"
b111 ,"
b1011 M
b1011 9
14
11
10
1-
1,
1)
1(
b1010 6
b1010 5
b1010 $
1#
#1150000000000
0#
#1200000000000
1O
1P
0N
b1001 6
b1011 5
b1011 $
b1100 9
b1100 M
b1 -"
b1 $"
b1 {
b1 r
b1 k
b1 b
b1 [
b11 R
1#
#1250000000000
0#
#1300000000000
0O
1W
1_
1g
1o
1w
1!"
1)"
0P
1Y
1`
0^
1i
1p
0n
1y
1""
0~
1+"
b111 R
b11 [
b11 b
b11 k
b11 r
b11 {
b11 $"
b11 -"
b1101 M
b1101 9
b1000 6
b1100 5
b1100 $
1#
#1350000000000
0#
#1400000000000
0)"
0!"
0w
0o
0g
0_
0W
0+"
0("
0""
0y
0v
0p
0i
0f
0`
0Y
0V
b111 6
b1101 5
b1101 $
b1110 9
b1110 M
b111 -"
b111 $"
b111 {
b111 r
b111 k
b111 b
b111 [
1#
#1450000000000
0#
#1500000000000
b1111 M
b1111 9
0&
b110 6
b1110 5
b1110 $
1#
#1550000000000
0#
#1600000000000
03
02
0/
0.
0+
0*
0'
b101 6
b1111 5
b1111 $
b10000 9
b10000 M
b110 S
1#
#1650000000000
0#
#1700000000000
1O
1Q
b100 S
b110 Z
b110 c
b110 j
b110 s
b110 z
b110 %"
b110 ,"
b10001 M
b10001 9
b100 6
b0 5
b10000 $
1#
#1750000000000
0#
#1800000000000
1)"
1!"
1w
1o
1g
1_
1W
0O
1*"
1("
1#"
1x
1v
1q
1h
1f
1a
1X
1V
0Q
1N
b11 6
0%
b1 5
b10001 $
b10010 9
b10010 M
b100 ,"
b100 %"
b100 z
b100 s
b100 j
b100 c
b100 Z
b0 S
1#
#1850000000000
0#
#1900000000000
0W
0_
0g
0o
0w
0!"
0)"
0X
0a
1^
0h
0q
1n
0x
0#"
1~
0*"
b110 R
b0 Z
b0 c
b0 j
b0 s
b0 z
b0 %"
b0 ,"
b10011 M
b10011 9
04
01
00
0-
0,
0)
0(
b10 6
b10 5
b10010 $
1#
#1950000000000
0#
#2000000000000
1O
1P
0N
b1 6
b11 5
b10011 $
b10100 9
b10100 M
b110 -"
b110 $"
b110 {
b110 r
b110 k
b110 b
b110 [
b100 R
1#
#2050000000000
0#
#2100000000000
0O
1W
1_
1g
1o
1w
1!"
1)"
0P
1Y
1`
0^
1i
1p
0n
1y
1""
0~
1+"
b0 R
b100 [
b100 b
b100 k
b100 r
b100 {
b100 $"
b100 -"
b10101 M
b10101 9
b0 6
b100 5
b10100 $
1#
#2150000000000
0#
#2200000000000
0)"
0!"
0w
0o
0g
0_
0W
0+"
0("
0""
0y
0v
0p
0i
0f
0`
0Y
0V
b1111 6
b101 5
b10101 $
b10110 9
b10110 M
b0 -"
b0 $"
b0 {
b0 r
b0 k
b0 b
b0 [
1#
#2250000000000
0#
#2300000000000
b10111 M
b10111 9
1&
b1110 6
b110 5
b10110 $
1#
#2350000000000
0#
#2400000000000
13
12
1/
1.
1+
1*
1'
b1101 6
b111 5
b10111 $
b11000 9
b11000 M
b1 S
1#
#2450000000000
0#
#2500000000000
1O
1Q
b11 S
b1 Z
b1 c
b1 j
b1 s
b1 z
b1 %"
b1 ,"
b11001 M
b11001 9
b1100 6
b1000 5
b11000 $
1#
#2550000000000
0#
#2600000000000
1)"
1!"
1w
1o
1g
1_
1W
0O
1*"
1("
1#"
1x
1v
1q
1h
1f
1a
1X
1V
0Q
1N
b1011 6
1%
b1001 5
b11001 $
b11010 9
b11010 M
b11 ,"
b11 %"
b11 z
b11 s
b11 j
b11 c
b11 Z
b111 S
1#
#2650000000000
0#
#2700000000000
0W
0_
0g
0o
0w
0!"
0)"
0X
0a
1^
0h
0q
1n
0x
0#"
1~
0*"
b1 R
b111 Z
b111 c
b111 j
b111 s
b111 z
b111 %"
b111 ,"
b11011 M
b11011 9
14
11
10
1-
1,
1)
1(
b1010 6
b1010 5
b11010 $
1#
#2750000000000
0#
#2800000000000
1O
1P
0N
b1001 6
b1011 5
b11011 $
b11100 9
b11100 M
b1 -"
b1 $"
b1 {
b1 r
b1 k
b1 b
b1 [
b11 R
1#
#2850000000000
0#
#2900000000000
0O
1W
1_
1g
1o
1w
1!"
1)"
0P
1Y
1`
0^
1i
1p
0n
1y
1""
0~
1+"
b111 R
b11 [
b11 b
b11 k
b11 r
b11 {
b11 $"
b11 -"
b11101 M
b11101 9
b1000 6
b1100 5
b11100 $
1#
#2950000000000
0#
#3000000000000
0)"
0!"
0w
0o
0g
0_
0W
0+"
0("
0""
0y
0v
0p
0i
0f
0`
0Y
0V
b111 6
b1101 5
b11101 $
b11110 9
b11110 M
b111 -"
b111 $"
b111 {
b111 r
b111 k
b111 b
b111 [
1#
#3050000000000
0#
#3100000000000
b11111 M
b11111 9
0&
b110 6
b1110 5
b11110 $
1#
#3150000000000
0#
#3200000000000
03
02
0/
0.
0+
0*
0'
b101 6
b1111 5
b11111 $
b100000 9
b100000 M
b110 S
1#
#3250000000000
0#
#3300000000000
1O
1Q
b100 S
b110 Z
b110 c
b110 j
b110 s
b110 z
b110 %"
b110 ,"
b100001 M
b100001 9
b100 6
b0 5
b100000 $
1#
#3350000000000
0#
#3400000000000
1)"
1!"
1w
1o
1g
1_
1W
0O
1*"
1("
1#"
1x
1v
1q
1h
1f
1a
1X
1V
0Q
1N
b11 6
0%
b1 5
b100001 $
b100010 9
b100010 M
b100 ,"
b100 %"
b100 z
b100 s
b100 j
b100 c
b100 Z
b0 S
1#
#3450000000000
0#
#3500000000000
0W
0_
0g
0o
0w
0!"
0)"
0X
0a
1^
0h
0q
1n
0x
0#"
1~
0*"
b110 R
b0 Z
b0 c
b0 j
b0 s
b0 z
b0 %"
b0 ,"
b100011 M
b100011 9
04
01
00
0-
0,
0)
0(
b10 6
b10 5
b100010 $
1#
#3550000000000
0#
#3600000000000
1O
1P
0N
b1 6
b11 5
b100011 $
b100100 9
b100100 M
b110 -"
b110 $"
b110 {
b110 r
b110 k
b110 b
b110 [
b100 R
1#
#3650000000000
0#
#3700000000000
0O
1W
1_
1g
1o
1w
1!"
1)"
0P
1Y
1`
0^
1i
1p
0n
1y
1""
0~
1+"
b0 R
b100 [
b100 b
b100 k
b100 r
b100 {
b100 $"
b100 -"
b100101 M
b100101 9
b0 6
b100 5
b100100 $
1#
#3750000000000
0#
#3800000000000
0)"
0!"
0w
0o
0g
0_
0W
0+"
0("
0""
0y
0v
0p
0i
0f
0`
0Y
0V
b1111 6
b101 5
b100101 $
b100110 9
b100110 M
b0 -"
b0 $"
b0 {
b0 r
b0 k
b0 b
b0 [
1#
#3850000000000
0#
#3900000000000
b100111 M
b100111 9
1&
b1110 6
b110 5
b100110 $
1#
#3950000000000
0#
#4000000000000
13
12
1/
1.
1+
1*
1'
b1101 6
b111 5
b100111 $
b101000 9
b101000 M
b1 S
1#
#4050000000000
0#
#4100000000000
1O
1Q
b11 S
b1 Z
b1 c
b1 j
b1 s
b1 z
b1 %"
b1 ,"
b101001 M
b101001 9
b1100 6
b1000 5
b101000 $
1#
#4150000000000
0#
#4200000000000
1)"
1!"
1w
1o
1g
1_
1W
0O
1*"
1("
1#"
1x
1v
1q
1h
1f
1a
1X
1V
0Q
1N
b1011 6
1%
b1001 5
b101001 $
b101010 9
b101010 M
b11 ,"
b11 %"
b11 z
b11 s
b11 j
b11 c
b11 Z
b111 S
1#
#4250000000000
0#
#4300000000000
0W
0_
0g
0o
0w
0!"
0)"
0X
0a
1^
0h
0q
1n
0x
0#"
1~
0*"
b1 R
b111 Z
b111 c
b111 j
b111 s
b111 z
b111 %"
b111 ,"
b101011 M
b101011 9
14
11
10
1-
1,
1)
1(
b1010 6
b1010 5
b101010 $
1#
#4350000000000
0#
#4400000000000
1O
1P
0N
b1001 6
b1011 5
b101011 $
b101100 9
b101100 M
b1 -"
b1 $"
b1 {
b1 r
b1 k
b1 b
b1 [
b11 R
1#
#4450000000000
0#
#4500000000000
0O
1W
1_
1g
1o
1w
1!"
1)"
0P
1Y
1`
0^
1i
1p
0n
1y
1""
0~
1+"
b111 R
b11 [
b11 b
b11 k
b11 r
b11 {
b11 $"
b11 -"
b101101 M
b101101 9
b1000 6
b1100 5
b101100 $
1#
#4550000000000
0#
#4600000000000
0)"
0!"
0w
0o
0g
0_
0W
0+"
0("
0""
0y
0v
0p
0i
0f
0`
0Y
0V
b111 6
b1101 5
b101101 $
b101110 9
b101110 M
b111 -"
b111 $"
b111 {
b111 r
b111 k
b111 b
b111 [
1#
#4650000000000
0#
#4700000000000
b101111 M
b101111 9
0&
b110 6
b1110 5
b101110 $
1#
#4750000000000
0#
#4800000000000
03
02
0/
0.
0+
0*
0'
b101 6
b1111 5
b101111 $
b110000 9
b110000 M
b110 S
1#
#4850000000000
0#
#4900000000000
1O
1Q
b100 S
b110 Z
b110 c
b110 j
b110 s
b110 z
b110 %"
b110 ,"
b110001 M
b110001 9
b100 6
b0 5
b110000 $
1#
#4950000000000
0#
#5000000000000
1)"
1!"
1w
1o
1g
1_
1W
0O
1*"
1("
1#"
1x
1v
1q
1h
1f
1a
1X
1V
0Q
1N
b11 6
0%
b1 5
b110001 $
b110010 9
b110010 M
b100 ,"
b100 %"
b100 z
b100 s
b100 j
b100 c
b100 Z
b0 S
1#
#5050000000000
0#
#5100000000000
0W
0_
0g
0o
0w
0!"
0)"
0X
0a
1^
0h
0q
1n
0x
0#"
1~
0*"
b110 R
b0 Z
b0 c
b0 j
b0 s
b0 z
b0 %"
b0 ,"
b110011 M
b110011 9
04
01
00
0-
0,
0)
0(
b10 6
b10 5
b110010 $
1#
#5150000000000
0#
#5200000000000
1O
1P
0N
b1 6
b11 5
b110011 $
b110100 9
b110100 M
b110 -"
b110 $"
b110 {
b110 r
b110 k
b110 b
b110 [
b100 R
1#
#5250000000000
0#
#5300000000000
0O
1W
1_
1g
1o
1w
1!"
1)"
0P
1Y
1`
0^
1i
1p
0n
1y
1""
0~
1+"
b0 R
b100 [
b100 b
b100 k
b100 r
b100 {
b100 $"
b100 -"
b110101 M
b110101 9
b0 6
b100 5
b110100 $
1#
#5350000000000
0#
#5400000000000
0)"
0!"
0w
0o
0g
0_
0W
0+"
0("
0""
0y
0v
0p
0i
0f
0`
0Y
0V
b1111 6
b101 5
b110101 $
b110110 9
b110110 M
b0 -"
b0 $"
b0 {
b0 r
b0 k
b0 b
b0 [
1#
#5450000000000
0#
#5500000000000
b110111 M
b110111 9
1&
b1110 6
b110 5
b110110 $
1#
#5550000000000
0#
#5600000000000
13
12
1/
1.
1+
1*
1'
b1101 6
b111 5
b110111 $
b111000 9
b111000 M
b1 S
1#
#5650000000000
0#
#5700000000000
1O
1Q
b11 S
b1 Z
b1 c
b1 j
b1 s
b1 z
b1 %"
b1 ,"
b111001 M
b111001 9
b1100 6
b1000 5
b111000 $
1#
#5750000000000
0#
#5800000000000
1)"
1!"
1w
1o
1g
1_
1W
0O
1*"
1("
1#"
1x
1v
1q
1h
1f
1a
1X
1V
0Q
1N
b1011 6
1%
b1001 5
b111001 $
b111010 9
b111010 M
b11 ,"
b11 %"
b11 z
b11 s
b11 j
b11 c
b11 Z
b111 S
1#
#5850000000000
0#
#5900000000000
0W
0_
0g
0o
0w
0!"
0)"
0X
0a
1^
0h
0q
1n
0x
0#"
1~
0*"
b1 R
b111 Z
b111 c
b111 j
b111 s
b111 z
b111 %"
b111 ,"
b111011 M
b111011 9
14
11
10
1-
1,
1)
1(
b1010 6
b1010 5
b111010 $
1#
#5950000000000
0#
#6000000000000
1O
1P
0N
b1001 6
b1011 5
b111011 $
b111100 9
b111100 M
b1 -"
b1 $"
b1 {
b1 r
b1 k
b1 b
b1 [
b11 R
1#
#6050000000000
0#
#6100000000000
0O
1W
1_
1g
1o
1w
1!"
1)"
0P
1Y
1`
0^
1i
1p
0n
1y
1""
0~
1+"
b111 R
b11 [
b11 b
b11 k
b11 r
b11 {
b11 $"
b11 -"
b111101 M
b111101 9
b1000 6
b1100 5
b111100 $
1#
#6150000000000
0#
#6200000000000
0)"
0!"
0w
0o
0g
0_
0W
0+"
0("
0""
0y
0v
0p
0i
0f
0`
0Y
0V
b111 6
b1101 5
b111101 $
b111110 9
b111110 M
b111 -"
b111 $"
b111 {
b111 r
b111 k
b111 b
b111 [
1#
#6250000000000
0#
#6300000000000
b111111 M
b111111 9
0&
b110 6
b1110 5
b111110 $
1#
#6350000000000
0#
#6400000000000
03
02
0/
0.
0+
0*
0'
b101 6
b1111 5
b111111 $
b1000000 9
b1000000 M
b110 S
1#
#6450000000000
0#
#6500000000000
1O
1Q
b100 S
b110 Z
b110 c
b110 j
b110 s
b110 z
b110 %"
b110 ,"
b1000001 M
b1000001 9
b100 6
b0 5
b1000000 $
1#
#6550000000000
0#
